ultrasonido/ControlLed.v
module ControlLed(
    input clk,
    input wire [19:0] contador2,  
    output reg sens_ult 
     
);

// distancia = 340 m/s * tiempo / 2
// 5cm => 295 us = 295000 ns = 14750 ciclos de reloj
// 1cm => 59 us = 59000 ns = 2950 ciclos de reloj

initial begin
	sens_ult=0; 
end


parameter L=14'd14750; //Para 5cm
parameter Lm=14'd2950; //Para 1cm



always @(posedge clk) 
	begin

		if (contador2>Lm && contador2<L)
			begin
				sens_ult=1; 
			end
	    else 
		begin
			sens_ult=0;
		end
	end
	

endmodule

ultrasonido/ControlLed_tb.v
`timescale 1ns / 1ps

module ControlLed_tb;

    // Declara las señales de entrada y salida para el módulo ControlLed
    reg clk;
    reg [19:0] contador2;
    wire sens_ult;

    // Crea una instancia del módulo ControlLed
    ControlLed UUT (
        .clk(clk),
        .contador2(contador2),
        .sens_ult(sens_ult)
    );

    // Genera una señal de reloj
    initial begin
        clk = 0;
        forever #10 clk = ~clk;
    end

    // Test sequence
    initial begin
        // Inicializa las señales
        contador2 = 0;

        // Espera 100 ns
        #100;

        // Incrementa contador2 durante 60000 ciclos de reloj
        for (contador2 = 0; contador2 < 60000; contador2 = contador2 + 1) begin
            #10;
        end

        // Finaliza la simulación
        #100 $finish;
    end

    initial begin
        $dumpfile("ControlLed_tb.vcd");
        $dumpvars(0, ControlLed_tb);
        
    end

endmodule

ultrasonido/ControlLed_tb.vcd
$date
	Thu Aug 29 20:51:47 2024
$end
$version
	Icarus Verilog
$end
$timescale
	1ps
$end
$scope module ControlLed_tb $end
$var wire 1 ! sens_ult $end
$var reg 1 " clk $end
$var reg 20 # contador2 [19:0] $end
$scope module UUT $end
$var wire 1 " clk $end
$var wire 20 $ contador2 [19:0] $end
$var reg 1 ! sens_ult $end
$upscope $end
$upscope $end
$enddefinitions $end
#0
$dumpvars
b0 $
b0 #
0"
0!
$end
#10000
1"
#20000
0"
#30000
1"
#40000
0"
#50000
1"
#60000
0"
#70000
1"
#80000
0"
#90000
1"
#100000
0"
#110000
1"
b1 #
b1 $
#120000
0"
b10 #
b10 $
#130000
1"
b11 #
b11 $
#140000
0"
b100 #
b100 $
#150000
1"
b101 #
b101 $
#160000
0"
b110 #
b110 $
#170000
1"
b111 #
b111 $
#180000
0"
b1000 #
b1000 $
#190000
1"
b1001 #
b1001 $
#200000
0"
b1010 #
b1010 $
#210000
1"
b1011 #
b1011 $
#220000
0"
b1100 #
b1100 $
#230000
1"
b1101 #
b1101 $
#240000
0"
b1110 #
b1110 $
#250000
1"
b1111 #
b1111 $
#260000
0"
b10000 #
b10000 $
#270000
1"
b10001 #
b10001 $
#280000
0"
b10010 #
b10010 $
#290000
1"
b10011 #
b10011 $
#300000
0"
b10100 #
b10100 $
#310000
1"
b10101 #
b10101 $
#320000
0"
b10110 #
b10110 $
#330000
1"
b10111 #
b10111 $
#340000
0"
b11000 #
b11000 $
#350000
1"
b11001 #
b11001 $
#360000
0"
b11010 #
b11010 $
#370000
1"
b11011 #
b11011 $
#380000
0"
b11100 #
b11100 $
#390000
1"
b11101 #
b11101 $
#400000
0"
b11110 #
b11110 $
#410000
1"
b11111 #
b11111 $
#420000
0"
b100000 #
b100000 $
#430000
1"
b100001 #
b100001 $
#440000
0"
b100010 #
b100010 $
#450000
1"
b100011 #
b100011 $
#460000
0"
b100100 #
b100100 $
#470000
1"
b100101 #
b100101 $
#480000
0"
b100110 #
b100110 $
#490000
1"
b100111 #
b100111 $
#500000
0"
b101000 #
b101000 $
#510000
1"
b101001 #
b101001 $
#520000
0"
b101010 #
b101010 $
#530000
1"
b101011 #
b101011 $
#540000
0"
b101100 #
b101100 $
#550000
1"
b101101 #
b101101 $
#560000
0"
b101110 #
b101110 $
#570000
1"
b101111 #
b101111 $
#580000
0"
b110000 #
b110000 $
#590000
1"
b110001 #
b110001 $
#600000
0"
b110010 #
b110010 $
#610000
1"
b110011 #
b110011 $
#620000
0"
b110100 #
b110100 $
#630000
1"
b110101 #
b110101 $
#640000
0"
b110110 #
b110110 $
#650000
1"
b110111 #
b110111 $
#660000
0"
b111000 #
b111000 $
#670000
1"
b111001 #
b111001 $
#680000
0"
b111010 #
b111010 $
#690000
1"
b111011 #
b111011 $
#700000
0"
b111100 #
b111100 $
#710000
1"
b111101 #
b111101 $
#720000
0"
b111110 #
b111110 $
#730000
1"
b111111 #
b111111 $
#740000
0"
b1000000 #
b1000000 $
#750000
1"
b1000001 #
b1000001 $
#760000
0"
b1000010 #
b1000010 $
#770000
1"
b1000011 #
b1000011 $
#780000
0"
b1000100 #
b1000100 $
#790000
1"
b1000101 #
b1000101 $
#800000
0"
b1000110 #
b1000110 $
#810000
1"
b1000111 #
b1000111 $
#820000
0"
b1001000 #
b1001000 $
#830000
1"
b1001001 #
b1001001 $
#840000
0"
b1001010 #
b1001010 $
#850000
1"
b1001011 #
b1001011 $
#860000
0"
b1001100 #
b1001100 $
#870000
1"
b1001101 #
b1001101 $
#880000
0"
b1001110 #
b1001110 $
#890000
1"
b1001111 #
b1001111 $
#900000
0"
b1010000 #
b1010000 $
#910000
1"
b1010001 #
b1010001 $
#920000
0"
b1010010 #
b1010010 $
#930000
1"
b1010011 #
b1010011 $
#940000
0"
b1010100 #
b1010100 $
#950000
1"
b1010101 #
b1010101 $
#960000
0"
b1010110 #
b1010110 $
#970000
1"
b1010111 #
b1010111 $
#980000
0"
b1011000 #
b1011000 $
#990000
1"
b1011001 #
b1011001 $
#1000000
0"
b1011010 #
b1011010 $
#1010000
1"
b1011011 #
b1011011 $
#1020000
0"
b1011100 #
b1011100 $
#1030000
1"
b1011101 #
b1011101 $
#1040000
0"
b1011110 #
b1011110 $
#1050000
1"
b1011111 #
b1011111 $
#1060000
0"
b1100000 #
b1100000 $
#1070000
1"
b1100001 #
b1100001 $
#1080000
0"
b1100010 #
b1100010 $
#1090000
1"
b1100011 #
b1100011 $
#1100000
0"
b1100100 #
b1100100 $
#1110000
1"
b1100101 #
b1100101 $
#1120000
0"
b1100110 #
b1100110 $
#1130000
1"
b1100111 #
b1100111 $
#1140000
0"
b1101000 #
b1101000 $
#1150000
1"
b1101001 #
b1101001 $
#1160000
0"
b1101010 #
b1101010 $
#1170000
1"
b1101011 #
b1101011 $
#1180000
0"
b1101100 #
b1101100 $
#1190000
1"
b1101101 #
b1101101 $
#1200000
0"
b1101110 #
b1101110 $
#1210000
1"
b1101111 #
b1101111 $
#1220000
0"
b1110000 #
b1110000 $
#1230000
1"
b1110001 #
b1110001 $
#1240000
0"
b1110010 #
b1110010 $
#1250000
1"
b1110011 #
b1110011 $
#1260000
0"
b1110100 #
b1110100 $
#1270000
1"
b1110101 #
b1110101 $
#1280000
0"
b1110110 #
b1110110 $
#1290000
1"
b1110111 #
b1110111 $
#1300000
0"
b1111000 #
b1111000 $
#1310000
1"
b1111001 #
b1111001 $
#1320000
0"
b1111010 #
b1111010 $
#1330000
1"
b1111011 #
b1111011 $
#1340000
0"
b1111100 #
b1111100 $
#1350000
1"
b1111101 #
b1111101 $
#1360000
0"
b1111110 #
b1111110 $
#1370000
1"
b1111111 #
b1111111 $
#1380000
0"
b10000000 #
b10000000 $
#1390000
1"
b10000001 #
b10000001 $
#1400000
0"
b10000010 #
b10000010 $
#1410000
1"
b10000011 #
b10000011 $
#1420000
0"
b10000100 #
b10000100 $
#1430000
1"
b10000101 #
b10000101 $
#1440000
0"
b10000110 #
b10000110 $
#1450000
1"
b10000111 #
b10000111 $
#1460000
0"
b10001000 #
b10001000 $
#1470000
1"
b10001001 #
b10001001 $
#1480000
0"
b10001010 #
b10001010 $
#1490000
1"
b10001011 #
b10001011 $
#1500000
0"
b10001100 #
b10001100 $
#1510000
1"
b10001101 #
b10001101 $
#1520000
0"
b10001110 #
b10001110 $
#1530000
1"
b10001111 #
b10001111 $
#1540000
0"
b10010000 #
b10010000 $
#1550000
1"
b10010001 #
b10010001 $
#1560000
0"
b10010010 #
b10010010 $
#1570000
1"
b10010011 #
b10010011 $
#1580000
0"
b10010100 #
b10010100 $
#1590000
1"
b10010101 #
b10010101 $
#1600000
0"
b10010110 #
b10010110 $
#1610000
1"
b10010111 #
b10010111 $
#1620000
0"
b10011000 #
b10011000 $
#1630000
1"
b10011001 #
b10011001 $
#1640000
0"
b10011010 #
b10011010 $
#1650000
1"
b10011011 #
b10011011 $
#1660000
0"
b10011100 #
b10011100 $
#1670000
1"
b10011101 #
b10011101 $
#1680000
0"
b10011110 #
b10011110 $
#1690000
1"
b10011111 #
b10011111 $
#1700000
0"
b10100000 #
b10100000 $
#1710000
1"
b10100001 #
b10100001 $
#1720000
0"
b10100010 #
b10100010 $
#1730000
1"
b10100011 #
b10100011 $
#1740000
0"
b10100100 #
b10100100 $
#1750000
1"
b10100101 #
b10100101 $
#1760000
0"
b10100110 #
b10100110 $
#1770000
1"
b10100111 #
b10100111 $
#1780000
0"
b10101000 #
b10101000 $
#1790000
1"
b10101001 #
b10101001 $
#1800000
0"
b10101010 #
b10101010 $
#1810000
1"
b10101011 #
b10101011 $
#1820000
0"
b10101100 #
b10101100 $
#1830000
1"
b10101101 #
b10101101 $
#1840000
0"
b10101110 #
b10101110 $
#1850000
1"
b10101111 #
b10101111 $
#1860000
0"
b10110000 #
b10110000 $
#1870000
1"
b10110001 #
b10110001 $
#1880000
0"
b10110010 #
b10110010 $
#1890000
1"
b10110011 #
b10110011 $
#1900000
0"
b10110100 #
b10110100 $
#1910000
1"
b10110101 #
b10110101 $
#1920000
0"
b10110110 #
b10110110 $
#1930000
1"
b10110111 #
b10110111 $
#1940000
0"
b10111000 #
b10111000 $
#1950000
1"
b10111001 #
b10111001 $
#1960000
0"
b10111010 #
b10111010 $
#1970000
1"
b10111011 #
b10111011 $
#1980000
0"
b10111100 #
b10111100 $
#1990000
1"
b10111101 #
b10111101 $
#2000000
0"
b10111110 #
b10111110 $
#2010000
1"
b10111111 #
b10111111 $
#2020000
0"
b11000000 #
b11000000 $
#2030000
1"
b11000001 #
b11000001 $
#2040000
0"
b11000010 #
b11000010 $
#2050000
1"
b11000011 #
b11000011 $
#2060000
0"
b11000100 #
b11000100 $
#2070000
1"
b11000101 #
b11000101 $
#2080000
0"
b11000110 #
b11000110 $
#2090000
1"
b11000111 #
b11000111 $
#2100000
0"
b11001000 #
b11001000 $
#2110000
1"
b11001001 #
b11001001 $
#2120000
0"
b11001010 #
b11001010 $
#2130000
1"
b11001011 #
b11001011 $
#2140000
0"
b11001100 #
b11001100 $
#2150000
1"
b11001101 #
b11001101 $
#2160000
0"
b11001110 #
b11001110 $
#2170000
1"
b11001111 #
b11001111 $
#2180000
0"
b11010000 #
b11010000 $
#2190000
1"
b11010001 #
b11010001 $
#2200000
0"
b11010010 #
b11010010 $
#2210000
1"
b11010011 #
b11010011 $
#2220000
0"
b11010100 #
b11010100 $
#2230000
1"
b11010101 #
b11010101 $
#2240000
0"
b11010110 #
b11010110 $
#2250000
1"
b11010111 #
b11010111 $
#2260000
0"
b11011000 #
b11011000 $
#2270000
1"
b11011001 #
b11011001 $
#2280000
0"
b11011010 #
b11011010 $
#2290000
1"
b11011011 #
b11011011 $
#2300000
0"
b11011100 #
b11011100 $
#2310000
1"
b11011101 #
b11011101 $
#2320000
0"
b11011110 #
b11011110 $
#2330000
1"
b11011111 #
b11011111 $
#2340000
0"
b11100000 #
b11100000 $
#2350000
1"
b11100001 #
b11100001 $
#2360000
0"
b11100010 #
b11100010 $
#2370000
1"
b11100011 #
b11100011 $
#2380000
0"
b11100100 #
b11100100 $
#2390000
1"
b11100101 #
b11100101 $
#2400000
0"
b11100110 #
b11100110 $
#2410000
1"
b11100111 #
b11100111 $
#2420000
0"
b11101000 #
b11101000 $
#2430000
1"
b11101001 #
b11101001 $
#2440000
0"
b11101010 #
b11101010 $
#2450000
1"
b11101011 #
b11101011 $
#2460000
0"
b11101100 #
b11101100 $
#2470000
1"
b11101101 #
b11101101 $
#2480000
0"
b11101110 #
b11101110 $
#2490000
1"
b11101111 #
b11101111 $
#2500000
0"
b11110000 #
b11110000 $
#2510000
1"
b11110001 #
b11110001 $
#2520000
0"
b11110010 #
b11110010 $
#2530000
1"
b11110011 #
b11110011 $
#2540000
0"
b11110100 #
b11110100 $
#2550000
1"
b11110101 #
b11110101 $
#2560000
0"
b11110110 #
b11110110 $
#2570000
1"
b11110111 #
b11110111 $
#2580000
0"
b11111000 #
b11111000 $
#2590000
1"
b11111001 #
b11111001 $
#2600000
0"
b11111010 #
b11111010 $
#2610000
1"
b11111011 #
b11111011 $
#2620000
0"
b11111100 #
b11111100 $
#2630000
1"
b11111101 #
b11111101 $
#2640000
0"
b11111110 #
b11111110 $
#2650000
1"
b11111111 #
b11111111 $
#2660000
0"
b100000000 #
b100000000 $
#2670000
1"
b100000001 #
b100000001 $
#2680000
0"
b100000010 #
b100000010 $
#2690000
1"
b100000011 #
b100000011 $
#2700000
0"
b100000100 #
b100000100 $
#2710000
1"
b100000101 #
b100000101 $
#2720000
0"
b100000110 #
b100000110 $
#2730000
1"
b100000111 #
b100000111 $
#2740000
0"
b100001000 #
b100001000 $
#2750000
1"
b100001001 #
b100001001 $
#2760000
0"
b100001010 #
b100001010 $
#2770000
1"
b100001011 #
b100001011 $
#2780000
0"
b100001100 #
b100001100 $
#2790000
1"
b100001101 #
b100001101 $
#2800000
0"
b100001110 #
b100001110 $
#2810000
1"
b100001111 #
b100001111 $
#2820000
0"
b100010000 #
b100010000 $
#2830000
1"
b100010001 #
b100010001 $
#2840000
0"
b100010010 #
b100010010 $
#2850000
1"
b100010011 #
b100010011 $
#2860000
0"
b100010100 #
b100010100 $
#2870000
1"
b100010101 #
b100010101 $
#2880000
0"
b100010110 #
b100010110 $
#2890000
1"
b100010111 #
b100010111 $
#2900000
0"
b100011000 #
b100011000 $
#2910000
1"
b100011001 #
b100011001 $
#2920000
0"
b100011010 #
b100011010 $
#2930000
1"
b100011011 #
b100011011 $
#2940000
0"
b100011100 #
b100011100 $
#2950000
1"
b100011101 #
b100011101 $
#2960000
0"
b100011110 #
b100011110 $
#2970000
1"
b100011111 #
b100011111 $
#2980000
0"
b100100000 #
b100100000 $
#2990000
1"
b100100001 #
b100100001 $
#3000000
0"
b100100010 #
b100100010 $
#3010000
1"
b100100011 #
b100100011 $
#3020000
0"
b100100100 #
b100100100 $
#3030000
1"
b100100101 #
b100100101 $
#3040000
0"
b100100110 #
b100100110 $
#3050000
1"
b100100111 #
b100100111 $
#3060000
0"
b100101000 #
b100101000 $
#3070000
1"
b100101001 #
b100101001 $
#3080000
0"
b100101010 #
b100101010 $
#3090000
1"
b100101011 #
b100101011 $
#3100000
0"
b100101100 #
b100101100 $
#3110000
1"
b100101101 #
b100101101 $
#3120000
0"
b100101110 #
b100101110 $
#3130000
1"
b100101111 #
b100101111 $
#3140000
0"
b100110000 #
b100110000 $
#3150000
1"
b100110001 #
b100110001 $
#3160000
0"
b100110010 #
b100110010 $
#3170000
1"
b100110011 #
b100110011 $
#3180000
0"
b100110100 #
b100110100 $
#3190000
1"
b100110101 #
b100110101 $
#3200000
0"
b100110110 #
b100110110 $
#3210000
1"
b100110111 #
b100110111 $
#3220000
0"
b100111000 #
b100111000 $
#3230000
1"
b100111001 #
b100111001 $
#3240000
0"
b100111010 #
b100111010 $
#3250000
1"
b100111011 #
b100111011 $
#3260000
0"
b100111100 #
b100111100 $
#3270000
1"
b100111101 #
b100111101 $
#3280000
0"
b100111110 #
b100111110 $
#3290000
1"
b100111111 #
b100111111 $
#3300000
0"
b101000000 #
b101000000 $
#3310000
1"
b101000001 #
b101000001 $
#3320000
0"
b101000010 #
b101000010 $
#3330000
1"
b101000011 #
b101000011 $
#3340000
0"
b101000100 #
b101000100 $
#3350000
1"
b101000101 #
b101000101 $
#3360000
0"
b101000110 #
b101000110 $
#3370000
1"
b101000111 #
b101000111 $
#3380000
0"
b101001000 #
b101001000 $
#3390000
1"
b101001001 #
b101001001 $
#3400000
0"
b101001010 #
b101001010 $
#3410000
1"
b101001011 #
b101001011 $
#3420000
0"
b101001100 #
b101001100 $
#3430000
1"
b101001101 #
b101001101 $
#3440000
0"
b101001110 #
b101001110 $
#3450000
1"
b101001111 #
b101001111 $
#3460000
0"
b101010000 #
b101010000 $
#3470000
1"
b101010001 #
b101010001 $
#3480000
0"
b101010010 #
b101010010 $
#3490000
1"
b101010011 #
b101010011 $
#3500000
0"
b101010100 #
b101010100 $
#3510000
1"
b101010101 #
b101010101 $
#3520000
0"
b101010110 #
b101010110 $
#3530000
1"
b101010111 #
b101010111 $
#3540000
0"
b101011000 #
b101011000 $
#3550000
1"
b101011001 #
b101011001 $
#3560000
0"
b101011010 #
b101011010 $
#3570000
1"
b101011011 #
b101011011 $
#3580000
0"
b101011100 #
b101011100 $
#3590000
1"
b101011101 #
b101011101 $
#3600000
0"
b101011110 #
b101011110 $
#3610000
1"
b101011111 #
b101011111 $
#3620000
0"
b101100000 #
b101100000 $
#3630000
1"
b101100001 #
b101100001 $
#3640000
0"
b101100010 #
b101100010 $
#3650000
1"
b101100011 #
b101100011 $
#3660000
0"
b101100100 #
b101100100 $
#3670000
1"
b101100101 #
b101100101 $
#3680000
0"
b101100110 #
b101100110 $
#3690000
1"
b101100111 #
b101100111 $
#3700000
0"
b101101000 #
b101101000 $
#3710000
1"
b101101001 #
b101101001 $
#3720000
0"
b101101010 #
b101101010 $
#3730000
1"
b101101011 #
b101101011 $
#3740000
0"
b101101100 #
b101101100 $
#3750000
1"
b101101101 #
b101101101 $
#3760000
0"
b101101110 #
b101101110 $
#3770000
1"
b101101111 #
b101101111 $
#3780000
0"
b101110000 #
b101110000 $
#3790000
1"
b101110001 #
b101110001 $
#3800000
0"
b101110010 #
b101110010 $
#3810000
1"
b101110011 #
b101110011 $
#3820000
0"
b101110100 #
b101110100 $
#3830000
1"
b101110101 #
b101110101 $
#3840000
0"
b101110110 #
b101110110 $
#3850000
1"
b101110111 #
b101110111 $
#3860000
0"
b101111000 #
b101111000 $
#3870000
1"
b101111001 #
b101111001 $
#3880000
0"
b101111010 #
b101111010 $
#3890000
1"
b101111011 #
b101111011 $
#3900000
0"
b101111100 #
b101111100 $
#3910000
1"
b101111101 #
b101111101 $
#3920000
0"
b101111110 #
b101111110 $
#3930000
1"
b101111111 #
b101111111 $
#3940000
0"
b110000000 #
b110000000 $
#3950000
1"
b110000001 #
b110000001 $
#3960000
0"
b110000010 #
b110000010 $
#3970000
1"
b110000011 #
b110000011 $
#3980000
0"
b110000100 #
b110000100 $
#3990000
1"
b110000101 #
b110000101 $
#4000000
0"
b110000110 #
b110000110 $
#4010000
1"
b110000111 #
b110000111 $
#4020000
0"
b110001000 #
b110001000 $
#4030000
1"
b110001001 #
b110001001 $
#4040000
0"
b110001010 #
b110001010 $
#4050000
1"
b110001011 #
b110001011 $
#4060000
0"
b110001100 #
b110001100 $
#4070000
1"
b110001101 #
b110001101 $
#4080000
0"
b110001110 #
b110001110 $
#4090000
1"
b110001111 #
b110001111 $
#4100000
0"
b110010000 #
b110010000 $
#4110000
1"
b110010001 #
b110010001 $
#4120000
0"
b110010010 #
b110010010 $
#4130000
1"
b110010011 #
b110010011 $
#4140000
0"
b110010100 #
b110010100 $
#4150000
1"
b110010101 #
b110010101 $
#4160000
0"
b110010110 #
b110010110 $
#4170000
1"
b110010111 #
b110010111 $
#4180000
0"
b110011000 #
b110011000 $
#4190000
1"
b110011001 #
b110011001 $
#4200000
0"
b110011010 #
b110011010 $
#4210000
1"
b110011011 #
b110011011 $
#4220000
0"
b110011100 #
b110011100 $
#4230000
1"
b110011101 #
b110011101 $
#4240000
0"
b110011110 #
b110011110 $
#4250000
1"
b110011111 #
b110011111 $
#4260000
0"
b110100000 #
b110100000 $
#4270000
1"
b110100001 #
b110100001 $
#4280000
0"
b110100010 #
b110100010 $
#4290000
1"
b110100011 #
b110100011 $
#4300000
0"
b110100100 #
b110100100 $
#4310000
1"
b110100101 #
b110100101 $
#4320000
0"
b110100110 #
b110100110 $
#4330000
1"
b110100111 #
b110100111 $
#4340000
0"
b110101000 #
b110101000 $
#4350000
1"
b110101001 #
b110101001 $
#4360000
0"
b110101010 #
b110101010 $
#4370000
1"
b110101011 #
b110101011 $
#4380000
0"
b110101100 #
b110101100 $
#4390000
1"
b110101101 #
b110101101 $
#4400000
0"
b110101110 #
b110101110 $
#4410000
1"
b110101111 #
b110101111 $
#4420000
0"
b110110000 #
b110110000 $
#4430000
1"
b110110001 #
b110110001 $
#4440000
0"
b110110010 #
b110110010 $
#4450000
1"
b110110011 #
b110110011 $
#4460000
0"
b110110100 #
b110110100 $
#4470000
1"
b110110101 #
b110110101 $
#4480000
0"
b110110110 #
b110110110 $
#4490000
1"
b110110111 #
b110110111 $
#4500000
0"
b110111000 #
b110111000 $
#4510000
1"
b110111001 #
b110111001 $
#4520000
0"
b110111010 #
b110111010 $
#4530000
1"
b110111011 #
b110111011 $
#4540000
0"
b110111100 #
b110111100 $
#4550000
1"
b110111101 #
b110111101 $
#4560000
0"
b110111110 #
b110111110 $
#4570000
1"
b110111111 #
b110111111 $
#4580000
0"
b111000000 #
b111000000 $
#4590000
1"
b111000001 #
b111000001 $
#4600000
0"
b111000010 #
b111000010 $
#4610000
1"
b111000011 #
b111000011 $
#4620000
0"
b111000100 #
b111000100 $
#4630000
1"
b111000101 #
b111000101 $
#4640000
0"
b111000110 #
b111000110 $
#4650000
1"
b111000111 #
b111000111 $
#4660000
0"
b111001000 #
b111001000 $
#4670000
1"
b111001001 #
b111001001 $
#4680000
0"
b111001010 #
b111001010 $
#4690000
1"
b111001011 #
b111001011 $
#4700000
0"
b111001100 #
b111001100 $
#4710000
1"
b111001101 #
b111001101 $
#4720000
0"
b111001110 #
b111001110 $
#4730000
1"
b111001111 #
b111001111 $
#4740000
0"
b111010000 #
b111010000 $
#4750000
1"
b111010001 #
b111010001 $
#4760000
0"
b111010010 #
b111010010 $
#4770000
1"
b111010011 #
b111010011 $
#4780000
0"
b111010100 #
b111010100 $
#4790000
1"
b111010101 #
b111010101 $
#4800000
0"
b111010110 #
b111010110 $
#4810000
1"
b111010111 #
b111010111 $
#4820000
0"
b111011000 #
b111011000 $
#4830000
1"
b111011001 #
b111011001 $
#4840000
0"
b111011010 #
b111011010 $
#4850000
1"
b111011011 #
b111011011 $
#4860000
0"
b111011100 #
b111011100 $
#4870000
1"
b111011101 #
b111011101 $
#4880000
0"
b111011110 #
b111011110 $
#4890000
1"
b111011111 #
b111011111 $
#4900000
0"
b111100000 #
b111100000 $
#4910000
1"
b111100001 #
b111100001 $
#4920000
0"
b111100010 #
b111100010 $
#4930000
1"
b111100011 #
b111100011 $
#4940000
0"
b111100100 #
b111100100 $
#4950000
1"
b111100101 #
b111100101 $
#4960000
0"
b111100110 #
b111100110 $
#4970000
1"
b111100111 #
b111100111 $
#4980000
0"
b111101000 #
b111101000 $
#4990000
1"
b111101001 #
b111101001 $
#5000000
0"
b111101010 #
b111101010 $
#5010000
1"
b111101011 #
b111101011 $
#5020000
0"
b111101100 #
b111101100 $
#5030000
1"
b111101101 #
b111101101 $
#5040000
0"
b111101110 #
b111101110 $
#5050000
1"
b111101111 #
b111101111 $
#5060000
0"
b111110000 #
b111110000 $
#5070000
1"
b111110001 #
b111110001 $
#5080000
0"
b111110010 #
b111110010 $
#5090000
1"
b111110011 #
b111110011 $
#5100000
0"
b111110100 #
b111110100 $
#5110000
1"
b111110101 #
b111110101 $
#5120000
0"
b111110110 #
b111110110 $
#5130000
1"
b111110111 #
b111110111 $
#5140000
0"
b111111000 #
b111111000 $
#5150000
1"
b111111001 #
b111111001 $
#5160000
0"
b111111010 #
b111111010 $
#5170000
1"
b111111011 #
b111111011 $
#5180000
0"
b111111100 #
b111111100 $
#5190000
1"
b111111101 #
b111111101 $
#5200000
0"
b111111110 #
b111111110 $
#5210000
1"
b111111111 #
b111111111 $
#5220000
0"
b1000000000 #
b1000000000 $
#5230000
1"
b1000000001 #
b1000000001 $
#5240000
0"
b1000000010 #
b1000000010 $
#5250000
1"
b1000000011 #
b1000000011 $
#5260000
0"
b1000000100 #
b1000000100 $
#5270000
1"
b1000000101 #
b1000000101 $
#5280000
0"
b1000000110 #
b1000000110 $
#5290000
1"
b1000000111 #
b1000000111 $
#5300000
0"
b1000001000 #
b1000001000 $
#5310000
1"
b1000001001 #
b1000001001 $
#5320000
0"
b1000001010 #
b1000001010 $
#5330000
1"
b1000001011 #
b1000001011 $
#5340000
0"
b1000001100 #
b1000001100 $
#5350000
1"
b1000001101 #
b1000001101 $
#5360000
0"
b1000001110 #
b1000001110 $
#5370000
1"
b1000001111 #
b1000001111 $
#5380000
0"
b1000010000 #
b1000010000 $
#5390000
1"
b1000010001 #
b1000010001 $
#5400000
0"
b1000010010 #
b1000010010 $
#5410000
1"
b1000010011 #
b1000010011 $
#5420000
0"
b1000010100 #
b1000010100 $
#5430000
1"
b1000010101 #
b1000010101 $
#5440000
0"
b1000010110 #
b1000010110 $
#5450000
1"
b1000010111 #
b1000010111 $
#5460000
0"
b1000011000 #
b1000011000 $
#5470000
1"
b1000011001 #
b1000011001 $
#5480000
0"
b1000011010 #
b1000011010 $
#5490000
1"
b1000011011 #
b1000011011 $
#5500000
0"
b1000011100 #
b1000011100 $
#5510000
1"
b1000011101 #
b1000011101 $
#5520000
0"
b1000011110 #
b1000011110 $
#5530000
1"
b1000011111 #
b1000011111 $
#5540000
0"
b1000100000 #
b1000100000 $
#5550000
1"
b1000100001 #
b1000100001 $
#5560000
0"
b1000100010 #
b1000100010 $
#5570000
1"
b1000100011 #
b1000100011 $
#5580000
0"
b1000100100 #
b1000100100 $
#5590000
1"
b1000100101 #
b1000100101 $
#5600000
0"
b1000100110 #
b1000100110 $
#5610000
1"
b1000100111 #
b1000100111 $
#5620000
0"
b1000101000 #
b1000101000 $
#5630000
1"
b1000101001 #
b1000101001 $
#5640000
0"
b1000101010 #
b1000101010 $
#5650000
1"
b1000101011 #
b1000101011 $
#5660000
0"
b1000101100 #
b1000101100 $
#5670000
1"
b1000101101 #
b1000101101 $
#5680000
0"
b1000101110 #
b1000101110 $
#5690000
1"
b1000101111 #
b1000101111 $
#5700000
0"
b1000110000 #
b1000110000 $
#5710000
1"
b1000110001 #
b1000110001 $
#5720000
0"
b1000110010 #
b1000110010 $
#5730000
1"
b1000110011 #
b1000110011 $
#5740000
0"
b1000110100 #
b1000110100 $
#5750000
1"
b1000110101 #
b1000110101 $
#5760000
0"
b1000110110 #
b1000110110 $
#5770000
1"
b1000110111 #
b1000110111 $
#5780000
0"
b1000111000 #
b1000111000 $
#5790000
1"
b1000111001 #
b1000111001 $
#5800000
0"
b1000111010 #
b1000111010 $
#5810000
1"
b1000111011 #
b1000111011 $
#5820000
0"
b1000111100 #
b1000111100 $
#5830000
1"
b1000111101 #
b1000111101 $
#5840000
0"
b1000111110 #
b1000111110 $
#5850000
1"
b1000111111 #
b1000111111 $
#5860000
0"
b1001000000 #
b1001000000 $
#5870000
1"
b1001000001 #
b1001000001 $
#5880000
0"
b1001000010 #
b1001000010 $
#5890000
1"
b1001000011 #
b1001000011 $
#5900000
0"
b1001000100 #
b1001000100 $
#5910000
1"
b1001000101 #
b1001000101 $
#5920000
0"
b1001000110 #
b1001000110 $
#5930000
1"
b1001000111 #
b1001000111 $
#5940000
0"
b1001001000 #
b1001001000 $
#5950000
1"
b1001001001 #
b1001001001 $
#5960000
0"
b1001001010 #
b1001001010 $
#5970000
1"
b1001001011 #
b1001001011 $
#5980000
0"
b1001001100 #
b1001001100 $
#5990000
1"
b1001001101 #
b1001001101 $
#6000000
0"
b1001001110 #
b1001001110 $
#6010000
1"
b1001001111 #
b1001001111 $
#6020000
0"
b1001010000 #
b1001010000 $
#6030000
1"
b1001010001 #
b1001010001 $
#6040000
0"
b1001010010 #
b1001010010 $
#6050000
1"
b1001010011 #
b1001010011 $
#6060000
0"
b1001010100 #
b1001010100 $
#6070000
1"
b1001010101 #
b1001010101 $
#6080000
0"
b1001010110 #
b1001010110 $
#6090000
1"
b1001010111 #
b1001010111 $
#6100000
0"
b1001011000 #
b1001011000 $
#6110000
1"
b1001011001 #
b1001011001 $
#6120000
0"
b1001011010 #
b1001011010 $
#6130000
1"
b1001011011 #
b1001011011 $
#6140000
0"
b1001011100 #
b1001011100 $
#6150000
1"
b1001011101 #
b1001011101 $
#6160000
0"
b1001011110 #
b1001011110 $
#6170000
1"
b1001011111 #
b1001011111 $
#6180000
0"
b1001100000 #
b1001100000 $
#6190000
1"
b1001100001 #
b1001100001 $
#6200000
0"
b1001100010 #
b1001100010 $
#6210000
1"
b1001100011 #
b1001100011 $
#6220000
0"
b1001100100 #
b1001100100 $
#6230000
1"
b1001100101 #
b1001100101 $
#6240000
0"
b1001100110 #
b1001100110 $
#6250000
1"
b1001100111 #
b1001100111 $
#6260000
0"
b1001101000 #
b1001101000 $
#6270000
1"
b1001101001 #
b1001101001 $
#6280000
0"
b1001101010 #
b1001101010 $
#6290000
1"
b1001101011 #
b1001101011 $
#6300000
0"
b1001101100 #
b1001101100 $
#6310000
1"
b1001101101 #
b1001101101 $
#6320000
0"
b1001101110 #
b1001101110 $
#6330000
1"
b1001101111 #
b1001101111 $
#6340000
0"
b1001110000 #
b1001110000 $
#6350000
1"
b1001110001 #
b1001110001 $
#6360000
0"
b1001110010 #
b1001110010 $
#6370000
1"
b1001110011 #
b1001110011 $
#6380000
0"
b1001110100 #
b1001110100 $
#6390000
1"
b1001110101 #
b1001110101 $
#6400000
0"
b1001110110 #
b1001110110 $
#6410000
1"
b1001110111 #
b1001110111 $
#6420000
0"
b1001111000 #
b1001111000 $
#6430000
1"
b1001111001 #
b1001111001 $
#6440000
0"
b1001111010 #
b1001111010 $
