ultrasonido/ControlLed.v
module ControlLed(
    input clk,
    input wire [19:0] contador2,  
    output reg sens_ult 
     
);

// distancia = 340 m/s * tiempo / 2
// 5cm => 295 us = 295000 ns = 14750 ciclos de reloj
// 1cm => 59 us = 59000 ns = 2950 ciclos de reloj

initial begin
	sens_ult=0; 
end


parameter L=14'd14750; //Para 5cm
parameter Lm=14'd2950; //Para 1cm



always @(posedge clk) 
	begin

		if (contador2>Lm && contador2<L)
			begin
				sens_ult=1; 
			end
	    else 
		begin
			sens_ult=0;
		end
	end
	

endmodule

ultrasonido/ContadorConEcho.v
module ContadorConEcho(
    input wire clk,           // Entrada de reloj
    input wire echo,          // Entrada de control (cuando echo=1, se incrementa el contador)
    output reg [19:0] contador2 // Salida del contador de 32 bits
);

initial begin
	contador2 = 0; // Inicializa el contador
end

always @(posedge clk) 
    begin
		if(echo==1)
			begin
				contador2=contador2+1; //Se va almacenando en un contador si el ultrasonido genera el echo
			end
		else
			begin 
				contador2=0;
			end
	end

endmodule

ultrasonido/ContadorConTrigger.v
module ContadorConTrigger(
    input wire clk,  
    input wire echo,        
    output reg trigger       
);

// Limite 10us = 10000ns = 500 ciclos de reloj

reg [19:0] contador1;        
parameter limite = 20'd500;     

initial begin
    contador1 = 0;
    trigger = 0;
end

always @(negedge echo ) begin
    contador1 = 0;
    
end

always @(posedge clk) begin
    if (contador1 < limite) begin
        contador1 <= contador1 + 1;
        trigger <= 1;
    end else begin
        
        trigger = 0;
    end
end

endmodule

ultrasonido/top.v
module top (
  input clk,
  input echo,
  output trig,
  output sens_ult,
  output wire [19:0] s0
);

  


  
  // ContadorConTrigger
  ContadorConTrigger ContadorConTrigger_i0 (
    .clk( clk ), //in
    .echo( echo ), //in
    .trigger( trig ) //out
  );
  // ContadorConEcho
  ContadorConEcho ContadorConEcho_i1 (
    .clk( clk ),       //in
    .echo( echo ),     //in
    .contador2( s0 )   //out
  );
  // ControlLed
  ControlLed ControlLed_i2 (
    .clk( clk ),             //in
    .contador2( s0 ),        //in
    .sens_ult( sens_ult )    //out
  );

  
endmodule

ultrasonido/top_tb.v
`timescale 1ns / 1ps

module top_tb;

    
    reg clk;
    reg echo;
    wire trig;
    wire sens_ult;
    wire [19:0] s0;

    
    top uut (
        .clk(clk),
        .echo(echo),
        .trig(trig),
        .sens_ult(sens_ult),
        .s0(s0)
    );

    
    initial begin
        clk = 0;
        forever #10 clk = ~clk;
    end

    
    initial begin
        // Inicializa las señales
        echo = 0;

        // Espera 10 us del trig
        #10000;

        // Espera 25 us de los pulsos enviados por el ultrasonido
        #25000;

        // Activa echo
        echo = 1;
        #350000;

        // Desactiva echo
        echo = 0;
        // Espera 10 us del trig
        #10000;

        // Espera 25 us de los pulsos enviados por el ultrasonido
        #25000;


        // Activa echo de nuevo
        echo = 1;
        #50000;

        echo = 0;
        #50000;

        // Finaliza la simulación
        #100 $finish;
    end

    initial begin
        $dumpfile("top_tb.vcd");
        $dumpvars(0, top_tb);
    end

endmodule

ultrasonido/top_tb.vcd
$date
	Mon Sep  2 02:59:37 2024
$end
$version
	Icarus Verilog
$end
$timescale
	1ps
$end
$scope module top_tb $end
$var wire 1 ! trig $end
$var wire 1 " sens_ult $end
$var wire 20 # s0 [19:0] $end
$var reg 1 $ clk $end
$var reg 1 % echo $end
$scope module uut $end
$var wire 1 $ clk $end
$var wire 1 % echo $end
$var wire 1 ! trig $end
$var wire 1 " sens_ult $end
$var wire 20 & s0 [19:0] $end
$scope module ContadorConEcho_i1 $end
$var wire 1 $ clk $end
$var wire 1 % echo $end
$var reg 20 ' contador2 [19:0] $end
$upscope $end
$scope module ContadorConTrigger_i0 $end
$var wire 1 $ clk $end
$var wire 1 % echo $end
$var reg 20 ( contador1 [19:0] $end
$var reg 1 ! trigger $end
$upscope $end
$scope module ControlLed_i2 $end
$var wire 1 $ clk $end
$var wire 20 ) contador2 [19:0] $end
$var reg 1 " sens_ult $end
$upscope $end
$upscope $end
$upscope $end
$enddefinitions $end
#0
$dumpvars
b0 )
b0 (
b0 '
b0 &
0%
0$
b0 #
0"
0!
$end
#10000
1!
b1 (
1$
#20000
0$
#30000
b10 (
1$
#40000
0$
#50000
b11 (
1$
#60000
0$
#70000
b100 (
1$
#80000
0$
#90000
b101 (
1$
#100000
0$
#110000
b110 (
1$
#120000
0$
#130000
b111 (
1$
#140000
0$
#150000
b1000 (
1$
#160000
0$
#170000
b1001 (
1$
#180000
0$
#190000
b1010 (
1$
#200000
0$
#210000
b1011 (
1$
#220000
0$
#230000
b1100 (
1$
#240000
0$
#250000
b1101 (
1$
#260000
0$
#270000
b1110 (
1$
#280000
0$
#290000
b1111 (
1$
#300000
0$
#310000
b10000 (
1$
#320000
0$
#330000
b10001 (
1$
#340000
0$
#350000
b10010 (
1$
#360000
0$
#370000
b10011 (
1$
#380000
0$
#390000
b10100 (
1$
#400000
0$
#410000
b10101 (
1$
#420000
0$
#430000
b10110 (
1$
#440000
0$
#450000
b10111 (
1$
#460000
0$
#470000
b11000 (
1$
#480000
0$
#490000
b11001 (
1$
#500000
0$
#510000
b11010 (
1$
#520000
0$
#530000
b11011 (
1$
#540000
0$
#550000
b11100 (
1$
#560000
0$
#570000
b11101 (
1$
#580000
0$
#590000
b11110 (
1$
#600000
0$
#610000
b11111 (
1$
#620000
0$
#630000
b100000 (
1$
#640000
0$
#650000
b100001 (
1$
#660000
0$
#670000
b100010 (
1$
#680000
0$
#690000
b100011 (
1$
#700000
0$
#710000
b100100 (
1$
#720000
0$
#730000
b100101 (
1$
#740000
0$
#750000
b100110 (
1$
#760000
0$
#770000
b100111 (
1$
#780000
0$
#790000
b101000 (
1$
#800000
0$
#810000
b101001 (
1$
#820000
0$
#830000
b101010 (
1$
#840000
0$
#850000
b101011 (
1$
#860000
0$
#870000
b101100 (
1$
#880000
0$
#890000
b101101 (
1$
#900000
0$
#910000
b101110 (
1$
#920000
0$
#930000
b101111 (
1$
#940000
0$
#950000
b110000 (
1$
#960000
0$
#970000
b110001 (
1$
#980000
0$
#990000
b110010 (
1$
#1000000
0$
#1010000
b110011 (
1$
#1020000
0$
#1030000
b110100 (
1$
#1040000
0$
#1050000
b110101 (
1$
#1060000
0$
#1070000
b110110 (
1$
#1080000
0$
#1090000
b110111 (
1$
#1100000
0$
#1110000
b111000 (
1$
#1120000
0$
#1130000
b111001 (
1$
#1140000
0$
#1150000
b111010 (
1$
#1160000
0$
#1170000
b111011 (
1$
#1180000
0$
#1190000
b111100 (
1$
#1200000
0$
#1210000
b111101 (
1$
#1220000
0$
#1230000
b111110 (
1$
#1240000
0$
#1250000
b111111 (
1$
#1260000
0$
#1270000
b1000000 (
1$
#1280000
0$
#1290000
b1000001 (
1$
#1300000
0$
#1310000
b1000010 (
1$
#1320000
0$
#1330000
b1000011 (
1$
#1340000
0$
#1350000
b1000100 (
1$
#1360000
0$
#1370000
b1000101 (
1$
#1380000
0$
#1390000
b1000110 (
1$
#1400000
0$
#1410000
b1000111 (
1$
#1420000
0$
#1430000
b1001000 (
1$
#1440000
0$
#1450000
b1001001 (
1$
#1460000
0$
#1470000
b1001010 (
1$
#1480000
0$
#1490000
b1001011 (
1$
#1500000
0$
#1510000
b1001100 (
1$
#1520000
0$
#1530000
b1001101 (
1$
#1540000
0$
#1550000
b1001110 (
1$
#1560000
0$
#1570000
b1001111 (
1$
#1580000
0$
#1590000
b1010000 (
1$
#1600000
0$
#1610000
b1010001 (
1$
#1620000
0$
#1630000
b1010010 (
1$
#1640000
0$
#1650000
b1010011 (
1$
#1660000
0$
#1670000
b1010100 (
1$
#1680000
0$
#1690000
b1010101 (
1$
#1700000
0$
#1710000
b1010110 (
1$
#1720000
0$
#1730000
b1010111 (
1$
#1740000
0$
#1750000
b1011000 (
1$
#1760000
0$
#1770000
b1011001 (
1$
#1780000
0$
#1790000
b1011010 (
1$
#1800000
0$
#1810000
b1011011 (
1$
#1820000
0$
#1830000
b1011100 (
1$
#1840000
0$
#1850000
b1011101 (
1$
#1860000
0$
#1870000
b1011110 (
1$
#1880000
0$
#1890000
b1011111 (
1$
#1900000
0$
#1910000
b1100000 (
1$
#1920000
0$
#1930000
b1100001 (
1$
#1940000
0$
#1950000
b1100010 (
1$
#1960000
0$
#1970000
b1100011 (
1$
#1980000
0$
#1990000
b1100100 (
1$
#2000000
0$
#2010000
b1100101 (
1$
#2020000
0$
#2030000
b1100110 (
1$
#2040000
0$
#2050000
b1100111 (
1$
#2060000
0$
#2070000
b1101000 (
1$
#2080000
0$
#2090000
b1101001 (
1$
#2100000
0$
#2110000
b1101010 (
1$
#2120000
0$
#2130000
b1101011 (
1$
#2140000
0$
#2150000
b1101100 (
1$
#2160000
0$
#2170000
b1101101 (
1$
#2180000
0$
#2190000
b1101110 (
1$
#2200000
0$
#2210000
b1101111 (
1$
#2220000
0$
#2230000
b1110000 (
1$
#2240000
0$
#2250000
b1110001 (
1$
#2260000
0$
#2270000
b1110010 (
1$
#2280000
0$
#2290000
b1110011 (
1$
#2300000
0$
#2310000
b1110100 (
1$
#2320000
0$
#2330000
b1110101 (
1$
#2340000
0$
#2350000
b1110110 (
1$
#2360000
0$
#2370000
b1110111 (
1$
#2380000
0$
#2390000
b1111000 (
1$
#2400000
0$
#2410000
b1111001 (
1$
#2420000
0$
#2430000
b1111010 (
1$
#2440000
0$
#2450000
b1111011 (
1$
#2460000
0$
#2470000
b1111100 (
1$
#2480000
0$
#2490000
b1111101 (
1$
#2500000
0$
#2510000
b1111110 (
1$
#2520000
0$
#2530000
b1111111 (
1$
#2540000
0$
#2550000
b10000000 (
1$
#2560000
0$
#2570000
b10000001 (
1$
#2580000
0$
#2590000
b10000010 (
1$
#2600000
0$
#2610000
b10000011 (
1$
#2620000
0$
#2630000
b10000100 (
1$
#2640000
0$
#2650000
b10000101 (
1$
#2660000
0$
#2670000
b10000110 (
1$
#2680000
0$
#2690000
b10000111 (
1$
#2700000
0$
#2710000
b10001000 (
1$
#2720000
0$
#2730000
b10001001 (
1$
#2740000
0$
#2750000
b10001010 (
1$
#2760000
0$
#2770000
b10001011 (
1$
#2780000
0$
#2790000
b10001100 (
1$
#2800000
0$
#2810000
b10001101 (
1$
#2820000
0$
#2830000
b10001110 (
1$
#2840000
0$
#2850000
b10001111 (
1$
#2860000
0$
#2870000
b10010000 (
1$
#2880000
0$
#2890000
b10010001 (
1$
#2900000
0$
#2910000
b10010010 (
1$
#2920000
0$
#2930000
b10010011 (
1$
#2940000
0$
#2950000
b10010100 (
1$
#2960000
0$
#2970000
b10010101 (
1$
#2980000
0$
#2990000
b10010110 (
1$
#3000000
0$
#3010000
b10010111 (
1$
#3020000
0$
#3030000
b10011000 (
1$
#3040000
0$
#3050000
b10011001 (
1$
#3060000
0$
#3070000
b10011010 (
1$
#3080000
0$
#3090000
b10011011 (
1$
#3100000
0$
#3110000
b10011100 (
1$
#3120000
0$
#3130000
b10011101 (
1$
#3140000
0$
#3150000
b10011110 (
1$
#3160000
0$
#3170000
b10011111 (
1$
#3180000
0$
#3190000
b10100000 (
1$
#3200000
0$
#3210000
b10100001 (
1$
#3220000
0$
#3230000
b10100010 (
1$
#3240000
0$
#3250000
b10100011 (
1$
#3260000
0$
#3270000
b10100100 (
1$
#3280000
0$
#3290000
b10100101 (
1$
#3300000
0$
#3310000
b10100110 (
1$
#3320000
0$
#3330000
b10100111 (
1$
#3340000
0$
#3350000
b10101000 (
1$
#3360000
0$
#3370000
b10101001 (
1$
#3380000
0$
#3390000
b10101010 (
1$
#3400000
0$
#3410000
b10101011 (
1$
#3420000
0$
#3430000
b10101100 (
1$
#3440000
0$
#3450000
b10101101 (
1$
#3460000
0$
#3470000
b10101110 (
1$
#3480000
0$
#3490000
b10101111 (
1$
#3500000
0$
#3510000
b10110000 (
1$
#3520000
0$
#3530000
b10110001 (
1$
#3540000
0$
#3550000
b10110010 (
1$
#3560000
0$
#3570000
b10110011 (
1$
#3580000
0$
#3590000
b10110100 (
1$
#3600000
0$
#3610000
b10110101 (
1$
#3620000
0$
#3630000
b10110110 (
1$
#3640000
0$
#3650000
b10110111 (
1$
#3660000
0$
#3670000
b10111000 (
1$
#3680000
0$
#3690000
b10111001 (
1$
#3700000
0$
#3710000
b10111010 (
1$
#3720000
0$
#3730000
b10111011 (
1$
#3740000
0$
#3750000
b10111100 (
1$
#3760000
0$
#3770000
b10111101 (
1$
#3780000
0$
#3790000
b10111110 (
1$
#3800000
0$
#3810000
b10111111 (
1$
#3820000
0$
#3830000
b11000000 (
1$
#3840000
0$
#3850000
b11000001 (
1$
#3860000
0$
#3870000
b11000010 (
1$
#3880000
0$
#3890000
b11000011 (
1$
#3900000
0$
#3910000
b11000100 (
1$
#3920000
0$
#3930000
b11000101 (
1$
#3940000
0$
#3950000
b11000110 (
1$
#3960000
0$
#3970000
b11000111 (
1$
#3980000
0$
#3990000
b11001000 (
1$
#4000000
0$
#4010000
b11001001 (
1$
#4020000
0$
#4030000
b11001010 (
1$
#4040000
0$
#4050000
b11001011 (
1$
#4060000
0$
#4070000
b11001100 (
1$
#4080000
0$
#4090000
b11001101 (
1$
#4100000
0$
#4110000
b11001110 (
1$
#4120000
0$
#4130000
b11001111 (
1$
#4140000
0$
#4150000
b11010000 (
1$
#4160000
0$
#4170000
b11010001 (
1$
#4180000
0$
#4190000
b11010010 (
1$
#4200000
0$
#4210000
b11010011 (
1$
#4220000
0$
#4230000
b11010100 (
1$
#4240000
0$
#4250000
b11010101 (
1$
#4260000
0$
#4270000
b11010110 (
1$
#4280000
0$
#4290000
b11010111 (
1$
#4300000
0$
#4310000
b11011000 (
1$
#4320000
0$
#4330000
b11011001 (
1$
#4340000
0$
#4350000
b11011010 (
1$
#4360000
0$
#4370000
b11011011 (
1$
#4380000
0$
#4390000
b11011100 (
1$
#4400000
0$
#4410000
b11011101 (
1$
#4420000
0$
#4430000
b11011110 (
1$
#4440000
0$
#4450000
b11011111 (
1$
#4460000
0$
#4470000
b11100000 (
1$
#4480000
0$
#4490000
b11100001 (
1$
#4500000
0$
#4510000
b11100010 (
1$
#4520000
0$
#4530000
b11100011 (
1$
#4540000
0$
#4550000
b11100100 (
1$
#4560000
0$
#4570000
b11100101 (
1$
#4580000
0$
#4590000
b11100110 (
1$
#4600000
0$
#4610000
b11100111 (
1$
#4620000
0$
#4630000
b11101000 (
1$
#4640000
0$
#4650000
b11101001 (
1$
#4660000
0$
#4670000
b11101010 (
1$
#4680000
0$
#4690000
b11101011 (
1$
#4700000
0$
#4710000
b11101100 (
1$
#4720000
0$
#4730000
b11101101 (
1$
#4740000
0$
#4750000
b11101110 (
1$
#4760000
0$
#4770000
b11101111 (
1$
#4780000
0$
#4790000
b11110000 (
1$
#4800000
0$
#4810000
b11110001 (
1$
#4820000
0$
#4830000
b11110010 (
1$
#4840000
0$
#4850000
b11110011 (
1$
#4860000
0$
#4870000
b11110100 (
1$
#4880000
0$
#4890000
b11110101 (
1$
#4900000
0$
#4910000
b11110110 (
1$
#4920000
0$
#4930000
b11110111 (
1$
#4940000
0$
#4950000
b11111000 (
1$
#4960000
0$
#4970000
b11111001 (
1$
#4980000
0$
#4990000
b11111010 (
1$
#5000000
0$
#5010000
b11111011 (
1$
#5020000
0$
#5030000
b11111100 (
1$
#5040000
0$
#5050000
b11111101 (
1$
#5060000
0$
#5070000
b11111110 (
1$
#5080000
0$
#5090000
b11111111 (
1$
#5100000
0$
#5110000
b100000000 (
1$
#5120000
0$
#5130000
b100000001 (
1$
#5140000
0$
#5150000
b100000010 (
1$
#5160000
0$
#5170000
b100000011 (
1$
#5180000
0$
#5190000
b100000100 (
1$
#5200000
0$
#5210000
b100000101 (
1$
#5220000
0$
#5230000
b100000110 (
1$
#5240000
0$
#5250000
b100000111 (
1$
#5260000
0$
#5270000
b100001000 (
1$
#5280000
0$
#5290000
b100001001 (
1$
#5300000
0$
#5310000
b100001010 (
1$
#5320000
0$
#5330000
b100001011 (
1$
#5340000
0$
#5350000
b100001100 (
1$
#5360000
0$
#5370000
b100001101 (
1$
#5380000
0$
#5390000
b100001110 (
1$
#5400000
0$
#5410000
b100001111 (
1$
#5420000
0$
#5430000
b100010000 (
1$
#5440000
0$
#5450000
b100010001 (
1$
#5460000
0$
#5470000
b100010010 (
1$
#5480000
0$
#5490000
b100010011 (
1$
#5500000
0$
#5510000
b100010100 (
1$
#5520000
0$
#5530000
b100010101 (
1$
#5540000
0$
#5550000
b100010110 (
1$
#5560000
0$
#5570000
b100010111 (
1$
#5580000
0$
#5590000
b100011000 (
1$
#5600000
0$
#5610000
b100011001 (
1$
#5620000
0$
#5630000
b100011010 (
1$
#5640000
0$
#5650000
b100011011 (
1$
#5660000
0$
#5670000
b100011100 (
1$
#5680000
0$
#5690000
b100011101 (
1$
#5700000
0$
#5710000
b100011110 (
1$
#5720000
0$
#5730000
b100011111 (
1$
#5740000
0$
#5750000
b100100000 (
1$
#5760000
0$
#5770000
b100100001 (
1$
#5780000
0$
#5790000
b100100010 (
1$
#5800000
0$
#5810000
b100100011 (
1$
#5820000
0$
#5830000
b100100100 (
1$
#5840000
0$
#5850000
b100100101 (
1$
#5860000
0$
#5870000
b100100110 (
1$
#5880000
0$
#5890000
b100100111 (
1$
#5900000
0$
#5910000
b100101000 (
1$
#5920000
0$
#5930000
b100101001 (
1$
#5940000
0$
#5950000
b100101010 (
1$
#5960000
0$
#5970000
b100101011 (
1$
#5980000
0$
#5990000
b100101100 (
1$
#6000000
0$
#6010000
b100101101 (
1$
#6020000
0$
#6030000
b100101110 (
1$
#6040000
0$
#6050000
b100101111 (
1$
#6060000
0$
#6070000
b100110000 (
1$
#6080000
0$
#6090000
b100110001 (
1$
#6100000
0$
#6110000
b100110010 (
1$
#6120000
0$
#6130000
b100110011 (
1$
#6140000
0$
#6150000
b100110100 (
1$
#6160000
0$
#6170000
b100110101 (
1$
#6180000
0$
#6190000
b100110110 (
1$
#6200000
0$
#6210000
b100110111 (
1$
#6220000
0$
#6230000
b100111000 (
1$
#6240000
0$
#6250000
b100111001 (
1$
#6260000
0$
#6270000
b100111010 (
1$
#6280000
0$
#6290000
b100111011 (
1$
#6300000
0$
#6310000
b100111100 (
1$
#6320000
0$
#6330000
b100111101 (
1$
#6340000
0$
#6350000
b100111110 (
1$
#6360000
0$
#6370000
b100111111 (
1$
#6380000
0$
#6390000
b101000000 (
1$
#6400000
0$
#6410000
b101000001 (
1$
#6420000
0$
#6430000
b101000010 (
1$
#6440000
0$
#6450000
b101000011 (
1$
#6460000
0$
#6470000
b101000100 (
1$
#6480000
0$
#6490000
b101000101 (
1$
#6500000
0$
#6510000
b101000110 (
1$
#6520000
0$
#6530000
b101000111 (
1$
#6540000
0$
#6550000
b101001000 (
1$
#6560000
0$
#6570000
b101001001 (
1$
#6580000
0$
#6590000
b101001010 (
1$
#6600000
0$
#6610000
b101001011 (
1$
#6620000
0$
#6630000
b101001100 (
1$
#6640000
0$
#6650000
b101001101 (
1$
#6660000
0$
#6670000
b101001110 (
1$
#6680000
0$
#6690000
b101001111 (
1$
#6700000
0$
#6710000
b101010000 (
1$
#6720000
0$
#6730000
b101010001 (
1$
#6740000
0$
#6750000
b101010010 (
1$
#6760000
0$
#6770000
b101010011 (
1$
#6780000
0$
#6790000
b101010100 (
1$
#6800000
0$
#6810000
b101010101 (
1$
#6820000
0$
#6830000
b101010110 (
1$
#6840000
0$
#6850000
b101010111 (
1$
#6860000
0$
#6870000
b101011000 (
1$
#6880000
0$
#6890000
b101011001 (
1$
#6900000
0$
#6910000
b101011010 (
1$
#6920000
0$
#6930000
b101011011 (
1$
#6940000
0$
#6950000
b101011100 (
1$
#6960000
0$
#6970000
b101011101 (
1$
#6980000
0$
#6990000
b101011110 (
1$
#7000000
0$
#7010000
b101011111 (
1$
#7020000
0$
#7030000
b101100000 (
1$
#7040000
0$
#7050000
b101100001 (
1$
#7060000
0$
#7070000
b101100010 (
1$
#7080000
0$
#7090000
b101100011 (
1$
#7100000
0$
#7110000
b101100100 (
1$
#7120000
0$
#7130000
b101100101 (
1$
#7140000
0$
#7150000
b101100110 (
1$
#7160000
0$
#7170000
b101100111 (
1$
#7180000
0$
#7190000
b101101000 (
1$
#7200000
0$
#7210000
b101101001 (
1$
#7220000
0$
#7230000
b101101010 (
1$
#7240000
0$
#7250000
b101101011 (
1$
#7260000
0$
#7270000
b101101100 (
1$
#7280000
0$
#7290000
b101101101 (
1$
#7300000
0$
#7310000
b101101110 (
1$
#7320000
0$
#7330000
b101101111 (
1$
#7340000
0$
#7350000
b101110000 (
1$
#7360000
0$
#7370000
b101110001 (
1$
#7380000
0$
#7390000
b101110010 (
1$
#7400000
0$
#7410000
b101110011 (
1$
#7420000
0$
#7430000
b101110100 (
1$
#7440000
0$
#7450000
b101110101 (
1$
#7460000
0$
#7470000
b101110110 (
1$
#7480000
0$
#7490000
b101110111 (
1$
#7500000
0$
#7510000
b101111000 (
1$
#7520000
0$
#7530000
b101111001 (
1$
#7540000
0$
#7550000
b101111010 (
1$
#7560000
0$
#7570000
b101111011 (
1$
#7580000
0$
#7590000
b101111100 (
1$
#7600000
0$
#7610000
b101111101 (
1$
#7620000
0$
#7630000
b101111110 (
1$
#7640000
0$
#7650000
b101111111 (
1$
#7660000
0$
#7670000
b110000000 (
1$
#7680000
0$
#7690000
b110000001 (
1$
#7700000
0$
#7710000
b110000010 (
1$
#7720000
0$
#7730000
b110000011 (
1$
#7740000
0$
#7750000
b110000100 (
1$
#7760000
0$
#7770000
b110000101 (
1$
#7780000
0$
#7790000
b110000110 (
1$
#7800000
0$
#7810000
b110000111 (
1$
#7820000
0$
#7830000
b110001000 (
1$
#7840000
0$
#7850000
b110001001 (
1$
#7860000
0$
#7870000
b110001010 (
1$
#7880000
0$
#7890000
b110001011 (
1$
#7900000
0$
#7910000
b110001100 (
1$
#7920000
0$
#7930000
b110001101 (
1$
#7940000
0$
#7950000
b110001110 (
1$
#7960000
0$
#7970000
b110001111 (
1$
#7980000
0$
#7990000
b110010000 (
1$
#8000000
0$
#8010000
b110010001 (
1$
#8020000
0$
#8030000
b110010010 (
1$
#8040000
0$
#8050000
b110010011 (
1$
#8060000
0$
#8070000
b110010100 (
1$
#8080000
0$
#8090000
b110010101 (
1$
#8100000
0$
#8110000
b110010110 (
1$
#8120000
0$
#8130000
b110010111 (
1$
#8140000
0$
#8150000
b110011000 (
1$
#8160000
0$
#8170000
b110011001 (
1$
#8180000
0$
#8190000
b110011010 (
1$
#8200000
0$
#8210000
b110011011 (
1$
#8220000
0$
#8230000
b110011100 (
1$
#8240000
0$
#8250000
b110011101 (
1$
#8260000
0$
#8270000
b110011110 (
1$
#8280000
0$
#8290000
b110011111 (
1$
#8300000
0$
#8310000
b110100000 (
1$
#8320000
0$
#8330000
b110100001 (
1$
#8340000
0$
#8350000
b110100010 (
1$
#8360000
0$
#8370000
b110100011 (
1$
#8380000
0$
#8390000
b110100100 (
1$
#8400000
0$
#8410000
b110100101 (
1$
#8420000
0$
#8430000
b110100110 (
1$
#8440000
0$
#8450000
b110100111 (
1$
#8460000
0$
#8470000
b110101000 (
1$
#8480000
0$
#8490000
b110101001 (
1$
#8500000
0$
#8510000
b110101010 (
1$
#8520000
0$
#8530000
b110101011 (
1$
#8540000
0$
#8550000
b110101100 (
1$
#8560000
0$
#8570000
b110101101 (
1$
#8580000
0$
#8590000
b110101110 (
1$
#8600000
0$
#8610000
b110101111 (
1$
#8620000
0$
#8630000
b110110000 (
1$
#8640000
0$
#8650000
b110110001 (
1$
#8660000
0$
#8670000
b110110010 (
1$
#8680000
0$
#8690000
b110110011 (
1$
#8700000
0$
#8710000
b110110100 (
1$
#8720000
0$
#8730000
b110110101 (
1$
#8740000
0$
#8750000
b110110110 (
1$
#8760000
0$
#8770000
b110110111 (
1$
#8780000
0$
#8790000
b110111000 (
1$
#8800000
0$
#8810000
b110111001 (
1$
#8820000
0$
#8830000
b110111010 (
1$
#8840000
0$
#8850000
b110111011 (
1$
#8860000
0$
#8870000
b110111100 (
1$
#8880000
0$
#8890000
b110111101 (
1$
#8900000
0$
#8910000
b110111110 (
1$
#8920000
0$
#8930000
b110111111 (
1$
#8940000
0$
#8950000
b111000000 (
1$
#8960000
0$
#8970000
b111000001 (
1$
#8980000
0$
#8990000
b111000010 (
1$
#9000000
0$
#9010000
b111000011 (
1$
#9020000
0$
#9030000
b111000100 (
1$
#9040000
0$
#9050000
b111000101 (
1$
#9060000
0$
#9070000
b111000110 (
1$
#9080000
0$
#9090000
b111000111 (
1$
#9100000
0$
#9110000
b111001000 (
1$
#9120000
0$
#9130000
b111001001 (
1$
#9140000
0$
#9150000
b111001010 (
1$
#9160000
0$
#9170000
b111001011 (
1$
#9180000
0$
#9190000
b111001100 (
1$
#9200000
0$
#9210000
b111001101 (
1$
#9220000
0$
#9230000
b111001110 (
1$
#9240000
0$
#9250000
b111001111 (
1$
#9260000
0$
#9270000
b111010000 (
1$
#9280000
0$
#9290000
b111010001 (
1$
#9300000
0$
#9310000
b111010010 (
1$
#9320000
0$
#9330000
b111010011 (
1$
#9340000
0$
#9350000
b111010100 (
1$
#9360000
0$
#9370000
b111010101 (
1$
#9380000
0$
#9390000
b111010110 (
1$
#9400000
0$
#9410000
b111010111 (
1$
#9420000
0$
#9430000
b111011000 (
1$
#9440000
0$
#9450000
b111011001 (
1$
#9460000
0$
#9470000
b111011010 (
1$
#9480000
0$
#9490000
b111011011 (
1$
#9500000
0$
#9510000
b111011100 (
1$
#9520000
0$
#9530000
b111011101 (
1$
#9540000
0$
#9550000
b111011110 (
1$
#9560000
0$
#9570000
b111011111 (
1$
#9580000
0$
#9590000
b111100000 (
1$
#9600000
0$
#9610000
b111100001 (
1$
#9620000
0$
#9630000
b111100010 (
1$
#9640000
0$
#9650000
b111100011 (
1$
#9660000
0$
#9670000
b111100100 (
1$
#9680000
0$
#9690000
b111100101 (
1$
#9700000
0$
#9710000
b111100110 (
1$
#9720000
0$
#9730000
b111100111 (
1$
#9740000
0$
#9750000
b111101000 (
1$
#9760000
0$
#9770000
b111101001 (
1$
#9780000
0$
#9790000
b111101010 (
1$
#9800000
0$
#9810000
b111101011 (
1$
#9820000
0$
#9830000
b111101100 (
1$
#9840000
0$
#9850000
b111101101 (
1$
#9860000
0$
#9870000
b111101110 (
1$
#9880000
0$
#9890000
b111101111 (
1$
#9900000
0$
#9910000
b111110000 (
1$
#9920000
0$
#9930000
b111110001 (
1$
#9940000
0$
#9950000
b111110010 (
1$
#9960000
0$
#9970000
b111110011 (
1$
#9980000
0$
#9990000
b111110100 (
1$
#10000000
0$
#10010000
0!
1$
