JJDiaz/FSM/FSM.v
module tamagotchi_fsm (
    input wire btn_salud,
    input wire btn_energia,
    input wire btn_hambre,
    input wire btn_diversion,
    input wire btn_reset,
    input wire btn_test,        // Botón dedicado para activar el modo de prueba
    input wire clk,
    input wire [2:0] count_reset,  // Contador que varía entre 0 a 5 segundos para reset
    input wire [2:0] count_test,   // Contador que varía entre 0 a 5 segundos para test mode
    output reg [2:0] display_out
);

    // Definición de estados
    reg [3:0] niveles; // Niveles de cada estado
    reg [7:0] timer_salud, timer_energia, timer_hambre, timer_diversion; // Contadores de tiempo
    reg [1:0] btn_press_count; // Contador de presiones del botón
    reg test_mode; // Señal interna para modo de prueba

    // Inicialización de valores
    initial begin
        niveles = 4'b1010; // Todos los niveles en 10
        timer_salud = 0;
        timer_energia = 0;
        timer_hambre = 0;
        timer_diversion = 0;
        display_out = 3'b000; // Mostrar Salud y cara feliz por defecto
        btn_press_count = 2'b00; // Contador de presiones del botón
        test_mode = 1'b0; // Iniciar en modo normal
    end

    // Manejo del reset
    always @(posedge clk) begin
        if (count_reset == 3'b101) begin // 5 segundos en binario es 101
            niveles <= 4'b1010; // Reiniciar todos los niveles a 10
            display_out[2] <= 1'b1; // Cara feliz
            btn_press_count <= 2'b00; // Reiniciar contador de botones
            test_mode <= 1'b0; // Salir del modo de prueba
        end
    end

    // Manejo de la activación del modo test mediante el botón dedicado
    always @(posedge clk) begin
        if (btn_test && count_test == 3'b101) begin // 5 segundos en binario es 101
            test_mode <= 1'b1; // Activar modo de prueba
            btn_press_count <= 2'b00; // Reiniciar contador de botones
        end
    end

    // Manejo de los botones en modo normal o test
    always @(posedge clk) begin
        if (test_mode) begin
            // Modo test: Solo permitir niveles 1 o 10
            if (btn_salud) begin
                display_out[1:0] <= 2'b00; // Mostrar Salud
                if (btn_press_count == 2'b01) begin
                    niveles[3:2] <= (niveles[3:2] == 4'b0001) ? 4'b1010 : 4'b0001; // Alternar entre 1 y 10
                end
                btn_press_count <= btn_press_count + 1;
            end
            if (btn_energia) begin
                display_out[1:0] <= 2'b01; // Mostrar Energía
                if (btn_press_count == 2'b01) begin
                    niveles[3:2] <= (niveles[3:2] == 4'b0001) ? 4'b1010 : 4'b0001; // Alternar entre 1 y 10
                end
                btn_press_count <= btn_press_count + 1;
            end
            if (btn_hambre) begin
                display_out[1:0] <= 2'b10; // Mostrar Hambre
                if (btn_press_count == 2'b01) begin
                    niveles[3:2] <= (niveles[3:2] == 4'b0001) ? 4'b1010 : 4'b0001; // Alternar entre 1 y 10
                end
                btn_press_count <= btn_press_count + 1;
            end
            if (btn_diversion) begin
                display_out[1:0] <= 2'b11; // Mostrar Diversión
                if (btn_press_count == 2'b01) begin
                    niveles[3:2] <= (niveles[3:2] == 4'b0001) ? 4'b1010 : 4'b0001; // Alternar entre 1 y 10
                end
                btn_press_count <= btn_press_count + 1;
            end
        end else begin
            // Modo normal: Incrementar el nivel como antes
            if (btn_salud) begin
                display_out[1:0] <= 2'b00; // Mostrar Salud
                if (display_out[1:0] == 2'b00) begin
                    niveles[3:2] <= niveles[3:2] + 1; // Aumentar nivel Salud
                end
            end
            if (btn_energia) begin
                display_out[1:0] <= 2'b01; // Mostrar Energía
                if (display_out[1:0] == 2'b01) begin
                    niveles[3:2] <= niveles[3:2] + 1; // Aumentar nivel Energía
                end
            end
            if (btn_hambre) begin
                display_out[1:0] <= 2'b10; // Mostrar Hambre
                if (display_out[1:0] == 2'b10) begin
                    niveles[3:2] <= niveles[3:2] + 1; // Aumentar nivel Hambre
                end
            end
            if (btn_diversion) begin
                display_out[1:0] <= 2'b11; // Mostrar Diversión
                if (display_out[1:0] == 2'b11) begin
                    niveles[3:2] <= niveles[3:2] + 1; // Aumentar nivel Diversión
                end
            end
        end
    end

    // Manejo del decremento de los niveles en modo normal
    always @(posedge clk) begin
        if (!test_mode) begin
            if (timer_salud == 120) begin
                niveles[3:2] <= niveles[3:2] - 1;
                timer_salud <= 0;
            end else timer_salud <= timer_salud + 1;

            if (timer_energia == 100) begin
                niveles[3:2] <= niveles[3:2] - 1;
                timer_energia <= 0;
            end else timer_energia <= timer_energia + 1;

            if (timer_hambre == 70) begin
                niveles[3:2] <= niveles[3:2] - 1;
                timer_hambre <= 0;
            end else timer_hambre <= timer_hambre + 1;

            if (timer_diversion == 50) begin
                niveles[3:2] <= niveles[3:2] - 1;
                timer_diversion <= 0;
            end else timer_diversion <= timer_diversion + 1;
        end
    end

    // Actualizar cara feliz/triste basado en el nivel del estado actual
    always @(posedge clk) begin
        case (display_out[1:0])
            2'b00: display_out[2] <= (niveles[3:2] >= 4'd5) ? 1'b1 : 1'b0; // Salud
            2'b01: display_out[2] <= (niveles[3:2] >= 4'd5) ? 1'b1 : 1'b0; // Energía
            2'b10: display_out[2] <= (niveles[3:2] >= 4'd5) ? 1'b1 : 1'b0; // Hambre
            2'b11: display_out[2] <= (niveles[3:2] >= 4'd5) ? 1'b1 : 1'b0; // Diversión
        endcase
    end

endmodule

JJDiaz/FSM/FSM_tb.v
`timescale 1ns/1ps

module tamagotchi_tb;

    // Declaración de señales
    reg btn_salud;
    reg btn_energia;
    reg btn_hambre;
    reg btn_diversion;
    reg btn_reset;
    reg btn_test;
    reg clk;
    reg [2:0] count_reset;
    reg [2:0] count_test;
    wire [2:0] display_out;

    // Instancia del módulo tamagotchi_fsm
    tamagotchi_fsm uut (
        .btn_salud(btn_salud),
        .btn_energia(btn_energia),
        .btn_hambre(btn_hambre),
        .btn_diversion(btn_diversion),
        .btn_reset(btn_reset),
        .btn_test(btn_test),
        .clk(clk),
        .count_reset(count_reset),
        .count_test(count_test),
        .display_out(display_out)
    );

    // Generación del reloj
    initial begin
        clk = 0;
        forever #5 clk = ~clk; // Periodo de 10 ns
    end

    // Secuencia de test
    initial begin
        // Inicialización de señales
        btn_salud = 0;
        btn_energia = 0;
        btn_hambre = 0;
        btn_diversion = 0;
        btn_reset = 0;
        btn_test = 0;
        count_reset = 3'b000;
        count_test = 3'b000;

        // Esperar para estabilizar
        #20;

        // Simulación del comportamiento en modo normal
        // Presionar botón de salud
        btn_salud = 1;
        #10 btn_salud = 0;  // Liberar el botón
        #20;

        // Presionar botón de energía
        btn_energia = 1;
        #10 btn_energia = 0;  // Liberar el botón
        #20;

        // Presionar botón de hambre
        btn_hambre = 1;
        #10 btn_hambre = 0;  // Liberar el botón
        #20;

        // Presionar botón de diversión
        btn_diversion = 1;
        #10 btn_diversion = 0;  // Liberar el botón
        #20;

        // Finalizar simulación
        $finish;
    end

    // Guardar la salida en un archivo .vcd para visualización en GTKWave
    initial begin
        $dumpfile("tamagotchi_tb.vcd");
        $dumpvars(0, tamagotchi_tb);
    end

endmodule

JJDiaz/FSM/tamagotchi_tb.vcd
$date
	Wed Aug 21 22:53:47 2024
$end
$version
	Icarus Verilog
$end
$timescale
	1ps
$end
$scope module tamagotchi_tb $end
$var wire 3 ! display_out [2:0] $end
$var reg 1 " btn_diversion $end
$var reg 1 # btn_energia $end
$var reg 1 $ btn_hambre $end
$var reg 1 % btn_reset $end
$var reg 1 & btn_salud $end
$var reg 1 ' btn_test $end
$var reg 1 ( clk $end
$var reg 3 ) count_reset [2:0] $end
$var reg 3 * count_test [2:0] $end
$scope module uut $end
$var wire 1 " btn_diversion $end
$var wire 1 # btn_energia $end
$var wire 1 $ btn_hambre $end
$var wire 1 % btn_reset $end
$var wire 1 & btn_salud $end
$var wire 1 ' btn_test $end
$var wire 1 ( clk $end
$var wire 3 + count_reset [2:0] $end
$var wire 3 , count_test [2:0] $end
$var reg 2 - btn_press_count [1:0] $end
$var reg 3 . display_out [2:0] $end
$var reg 4 / niveles [3:0] $end
$var reg 1 0 test_mode $end
$var reg 8 1 timer_diversion [7:0] $end
$var reg 8 2 timer_energia [7:0] $end
$var reg 8 3 timer_hambre [7:0] $end
$var reg 8 4 timer_salud [7:0] $end
$upscope $end
$upscope $end
$enddefinitions $end
$comment Show the parameter values. $end
$dumpall
$end
#0
$dumpvars
b0 4
b0 3
b0 2
b0 1
00
b1000 /
b0 .
b0 -
b0 ,
b0 +
b0 *
b0 )
0(
0'
0&
0%
0$
0#
0"
b0 !
$end
#5000
b1 1
b1 3
b1 2
b1 4
1(
#10000
0(
#15000
b10 1
b10 3
b10 2
b10 4
1(
#20000
0(
1&
#25000
b1100 /
b11 1
b11 3
b11 2
b11 4
1(
#30000
0(
0&
#35000
b100 1
b100 3
b100 2
b100 4
1(
#40000
0(
#45000
b101 1
b101 3
b101 2
b101 4
1(
#50000
0(
1#
#55000
b110 1
b110 3
b110 2
b110 4
b1 !
b1 .
1(
#60000
0(
0#
#65000
b111 1
b111 3
b111 2
b111 4
1(
#70000
0(
#75000
b1000 1
b1000 3
b1000 2
b1000 4
1(
#80000
0(
1$
#85000
b10 !
b10 .
b1001 1
b1001 3
b1001 2
b1001 4
1(
#90000
0(
0$
#95000
b1010 1
b1010 3
b1010 2
b1010 4
1(
#100000
0(
#105000
b1011 1
b1011 3
b1011 2
b1011 4
1(
#110000
0(
1"
#115000
b1100 1
b1100 3
b1100 2
b1100 4
b11 !
b11 .
1(
#120000
0(
0"
#125000
b1101 1
b1101 3
b1101 2
b1101 4
1(
#130000
0(
#135000
b1110 1
b1110 3
b1110 2
b1110 4
1(
