JJDiaz/FSM/FSM.v
module tamagotchi_fsm (
    input wire btn_salud,
    input wire btn_energia,
    input wire btn_hambre,
    input wire btn_diversion,
    input wire btn_reset,
    input wire btn_test,
    input wire clk,
    input wire [2:0] count_reset,  // Contador que varía entre 0 a 5 segundos para reset
    input wire [2:0] count_test,   // Contador que varía entre 0 a 5 segundos para test mode
    output reg [2:0] display_out,
    output reg [6:0] seg_display  // Salida para la regleta de 7 segmentos
);

    // Definición de niveles separados para cada estado
    reg [3:0] nivel_salud;
    reg [3:0] nivel_energia;
    reg [3:0] nivel_hambre;
    reg [3:0] nivel_diversion;

    reg [7:0] timer_salud, timer_energia, timer_hambre, timer_diversion; // Contadores de tiempo
    reg [1:0] btn_press_count; // Contador de presiones del botón
    reg test_mode; // Señal interna para modo de prueba

    // Inicialización de valores
    initial begin
        nivel_salud = 4'b1000;   // Nivel de Salud inicial en 8
        nivel_energia = 4'b1000; // Nivel de Energía inicial en 8
        nivel_hambre = 4'b1000;  // Nivel de Hambre inicial en 8
        nivel_diversion = 4'b1000; // Nivel de Diversión inicial en 8
        timer_salud = 0;
        timer_energia = 0;
        timer_hambre = 0;
        timer_diversion = 0;
        display_out = 3'b000; // Mostrar Salud y cara feliz por defecto
        btn_press_count = 2'b00; // Contador de presiones del botón
        test_mode = 1'b0; // Iniciar en modo normal
        seg_display = 7'b0000000; // Inicializar la regleta de 7 segmentos en 0
    end

    // Manejo del reset
    always @(posedge clk) begin
        if (btn_reset) begin // 5 segundos en binario es 101
            nivel_salud <= 4'b1000;   // Reiniciar nivel de Salud a 8
            nivel_energia <= 4'b1000; // Reiniciar nivel de Energía a 8
            nivel_hambre <= 4'b1000;  // Reiniciar nivel de Hambre a 8
            nivel_diversion <= 4'b1000; // Reiniciar nivel de Diversión a 8
            display_out[2] <= 1'b1; // Cara feliz
            btn_press_count <= 2'b00; // Reiniciar contador de botones
            test_mode <= 1'b0; // Salir del modo de prueba
        end
    end

    // Manejo de la activación del modo test mediante el botón dedicado
    always @(posedge clk) begin
        if (btn_test) begin // 5 segundos en binario es 101
            test_mode <= 1'b1; // Activar modo de prueba
            btn_press_count <= 2'b00; // Reiniciar contador de botones
        end
    end

    // Manejo de los botones en modo normal o test, con niveles separados
    always @(posedge clk) begin
        if (test_mode) begin
            // Modo test: Solo permitir niveles 1 o 10
            if (btn_salud) begin
                display_out[1:0] <= 2'b00; // Mostrar Salud
                if (display_out == 3'b00 && nivel_salud != 'd1) begin
                    nivel_salud = 4'b0001;
                end
                if (display_out == 3'b00 && nivel_salud == 'd1) begin
                    nivel_salud = 4'b1010;
                end
            end
            if (btn_energia) begin
                display_out[1:0] <= 2'b01; // Mostrar Energía
                if (btn_press_count == 2'b01) begin
                    nivel_energia <= (nivel_energia == 4'b0001) ? 4'b1010 : 4'b0001; // Alternar entre 1 y 10
                end
                btn_press_count <= btn_press_count + 1;
            end
            if (btn_hambre) begin
                display_out[1:0] <= 2'b10; // Mostrar Hambre
                if (btn_press_count == 2'b01) begin
                    nivel_hambre <= (nivel_hambre == 4'b0001) ? 4'b1010 : 4'b0001; // Alternar entre 1 y 10
                end
                btn_press_count <= btn_press_count + 1;
            end
            if (btn_diversion) begin
                display_out[1:0] <= 2'b11; // Mostrar Diversión
                if (btn_press_count == 2'b01) begin
                    nivel_diversion <= (nivel_diversion == 4'b0001) ? 4'b1010 : 4'b0001; // Alternar entre 1 y 10
                end
                btn_press_count <= btn_press_count + 1;
            end
        end else begin
            // Modo normal: Incrementar el nivel del estado correspondiente, con límite de 10
            if (btn_salud) begin
                display_out[1:0] <= 2'b00; // Mostrar Salud
                btn_press_count <= btn_press_count + 1;
                if (nivel_salud < 4'b1010 && display_out == 3'b100) begin
                    nivel_salud <= nivel_salud + 1; // Aumentar nivel Salud
                    btn_press_count <= btn_press_count - 1; 
                end
            end
            if (btn_energia) begin
                display_out[1:0] <= 2'b01; // Mostrar Energía
                btn_press_count <= btn_press_count + 1;
                if (nivel_energia < 4'b1010 && display_out == 3'b101) begin
                    nivel_energia <= nivel_energia + 1; // Aumentar nivel Energía
                    btn_press_count <= btn_press_count - 1;
                end
            end
            if (btn_hambre) begin
                display_out[1:0] <= 2'b10; // Mostrar Hambre
                btn_press_count <= btn_press_count + 1;
                if (nivel_hambre < 4'b1010 && display_out == 3'b110) begin
                    nivel_hambre <= nivel_hambre + 1; // Aumentar nivel Hambre
                    btn_press_count <= btn_press_count - 1;
                end
            end
            if (btn_diversion) begin
                display_out[1:0] <= 2'b11; // Mostrar Diversión
                btn_press_count <= btn_press_count + 1;
                if (nivel_diversion < 4'b1010 && display_out == 3'b111) begin
                    nivel_diversion <= nivel_diversion + 1; // Aumentar nivel Diversión
                    btn_press_count <= btn_press_count - 1;
                end
            end
        end
    end

    // Manejo del decremento de los niveles en modo normal, con niveles separados
    always @(posedge clk) begin
        if (!test_mode) begin
            if (timer_salud == 120) begin
                nivel_salud <= nivel_salud - 1;
                timer_salud <= 0;
            end else timer_salud <= timer_salud + 1;

            if (timer_energia == 100) begin
                nivel_energia <= nivel_energia - 1;
                timer_energia <= 0;
            end else timer_energia <= timer_energia + 1;

            if (timer_hambre == 70) begin
                nivel_hambre <= nivel_hambre - 1;
                timer_hambre <= 0;
            end else timer_hambre <= timer_hambre + 1;

            if (timer_diversion == 50) begin
                nivel_diversion <= nivel_diversion - 1;
                timer_diversion <= 0;
            end else timer_diversion <= timer_diversion + 1;
        end
    end

    // Actualizar cara feliz/triste basado en el nivel del estado actual
    always @(posedge clk) begin
        case (display_out[1:0])
            2'b00: display_out[2] <= (nivel_salud >= 4'd5) ? 1'b1 : 1'b0; // Salud
            2'b01: display_out[2] <= (nivel_energia >= 4'd5) ? 1'b1 : 1'b0; // Energía
            2'b10: display_out[2] <= (nivel_hambre >= 4'd5) ? 1'b1 : 1'b0; // Hambre
            2'b11: display_out[2] <= (nivel_diversion >= 4'd5) ? 1'b1 : 1'b0; // Diversión
        endcase
    end

    // Control de la regleta de 7 segmentos para mostrar el nivel actual del estado seleccionado
    always @(posedge clk) begin
        case (display_out[1:0])
            2'b00: seg_display <= get_seg_display(nivel_salud);   // Mostrar nivel de Salud
            2'b01: seg_display <= get_seg_display(nivel_energia); // Mostrar nivel de Energía
            2'b10: seg_display <= get_seg_display(nivel_hambre);  // Mostrar nivel de Hambre
            2'b11: seg_display <= get_seg_display(nivel_diversion); // Mostrar nivel de Diversión
        endcase
    end

    // Función para convertir el nivel en el formato de 7 segmentos
    function [6:0] get_seg_display;
        input [3:0] level;
        case (level)
            4'b0000: get_seg_display = 7'b0111111; // 0
            4'b0001: get_seg_display = 7'b0000110; // 1
            4'b0010: get_seg_display = 7'b1011011; // 2
            4'b0011: get_seg_display = 7'b1001111; // 3
            4'b0100: get_seg_display = 7'b1100110; // 4
            4'b0101: get_seg_display = 7'b1101101; // 5
            4'b0110: get_seg_display = 7'b1111101; // 6
            4'b0111: get_seg_display = 7'b0000111; // 7
            4'b1000: get_seg_display = 7'b1111111; // 8
            4'b1001: get_seg_display = 7'b1101111; // 9
            4'b1010: get_seg_display = 7'b1110111; // A (utilizado para representar 10)
            default: get_seg_display = 7'b0000000; // Apagar todos los segmentos
        endcase
    endfunction

endmodule

JJDiaz/FSM/FSM_tb2.v
`timescale 1ns/1ps

module tamagotchi_tb;

    // Declaración de señales
    reg btn_salud;
    reg btn_energia;
    reg btn_hambre;
    reg btn_diversion;
    reg btn_reset;
    reg btn_test;
    reg clk;
    reg [2:0] count_reset;
    reg [2:0] count_test;
    wire [2:0] display_out;
    wire [6:0] seg_display;

    // Instancia del módulo tamagotchi_fsm
    tamagotchi_fsm uut (
        .btn_salud(btn_salud),
        .btn_energia(btn_energia),
        .btn_hambre(btn_hambre),
        .btn_diversion(btn_diversion),
        .btn_reset(btn_reset),
        .btn_test(btn_test),
        .clk(clk),
        .count_reset(count_reset),
        .count_test(count_test),
        .display_out(display_out),
        .seg_display(seg_display)
    );

    // Generación del reloj
    initial begin
        clk = 0;
        forever #5 clk = ~clk; // Periodo de 10 ns
    end

    // Secuencia de test
    initial begin
        // Inicialización de señales
        btn_salud = 0;
        btn_energia = 0;
        btn_hambre = 0;
        btn_diversion = 0;
        btn_reset = 0;
        btn_test = 0;
        count_reset = 3'b000;
        count_test = 3'b000;

        // Esperar para estabilizar
        #20;

        //Inicio de modo test
        btn_test = 1;
        #10 btn_test = 0;
        #20

        // Simulación del comportamiento: Primer botón Salud
        // Presionar botón de salud por primera vez
        btn_salud = 1;
        #10 btn_salud = 0;  // Liberar el botón
        #20;

        // Verificar cambio en display_out y seg_display
        $display("Salud - Primera presion: display_out = %b, seg_display = %b", display_out, seg_display);

        // Presionar botón de salud por segunda vez
        btn_salud = 1;
        #10 btn_salud = 0;  // Liberar el botón
        #20;

        // Verificar cambio en display_out y aumento en seg_display
        $display("Salud - Segunda presion: display_out = %b, seg_display = %b", display_out, seg_display);

        // Simulación del comportamiento: Botón Energía
        // Presionar botón de energía por primera vez
        btn_salud = 1;
        #10 btn_salud = 0;  // Liberar el botón
        #20;

        // Verificar cambio en display_out y seg_display
        $display("Energia - Primera presion: display_out = %b, seg_display = %b", display_out, seg_display);

        // Presionar botón de energía por segunda vez
        btn_salud = 1;
        #10 btn_salud = 0;  // Liberar el botón
        #20;

        // Verificar cambio en display_out y aumento en seg_display
        $display("Energia - Segunda presion: display_out = %b, seg_display = %b", display_out, seg_display);

        // Simulación del comportamiento: Primer botón Hambre
        // Presionar botón de hambre por primera vez
        btn_salud = 1;
        #10 btn_salud = 0;  // Liberar el botón
        #20;

        // Verificar cambio en display_out y seg_display
        $display("Hambre - Primera presion: display_out = %b, seg_display = %b", display_out, seg_display);

        // Presionar botón de hambre por segunda vez
        btn_salud = 1;
        #10 btn_salud = 0;  // Liberar el botón
        #20;

        // Verificar cambio en display_out y aumento en seg_display
        $display("Hambre - Segunda presion: display_out = %b, seg_display = %b", display_out, seg_display);

        // Simulación del comportamiento: Botón Diversion
        // Presionar botón de diversion por primera vez
        btn_diversion = 1;
        #10 btn_diversion = 0;  // Liberar el botón
        #20;

        // Verificar cambio en display_out y seg_display
        $display("Diversion - Primera presion: display_out = %b, seg_display = %b", display_out, seg_display);

        // Presionar botón de diversion por segunda vez
        btn_diversion = 1;
        #10 btn_diversion = 0;  // Liberar el botón
        #20;

        // Verificar cambio en display_out y aumento en seg_display
        $display("Diversion - Segunda presion: display_out = %b, seg_display = %b", display_out, seg_display);

        // Simulación del comportamiento: Botón Energía
        // Presionar botón de energía por primera vez
        btn_energia = 1;
        #10 btn_energia = 0;  // Liberar el botón
        #20;

        // Verificar cambio en display_out y seg_display
        $display("Energia - Primera presion: display_out = %b, seg_display = %b", display_out, seg_display);

        // Presionar botón de energía por segunda vez
        btn_energia = 1;
        #10 btn_energia = 0;  // Liberar el botón
        #20;

        // Verificar cambio en display_out y aumento en seg_display
        $display("Energia - Segunda presion: display_out = %b, seg_display = %b", display_out, seg_display);

        btn_reset = 1;
        #10 btn_reset = 0;
        #20

        // Finalizar simulación
        $finish;
    end

    // Guardar la salida en un archivo .vcd para visualización en GTKWave
    initial begin
        $dumpfile("tamagotchi_tb.vcd");
        $dumpvars(0, tamagotchi_tb);
    end

endmodule

JJDiaz/FSM/tamagotchi_tb.vcd
$date
	Thu Aug 29 18:31:39 2024
$end
$version
	Icarus Verilog
$end
$timescale
	1ps
$end
$scope module tamagotchi_tb $end
$var wire 7 ! seg_display [6:0] $end
$var wire 3 " display_out [2:0] $end
$var reg 1 # btn_diversion $end
$var reg 1 $ btn_energia $end
$var reg 1 % btn_hambre $end
$var reg 1 & btn_reset $end
$var reg 1 ' btn_salud $end
$var reg 1 ( btn_test $end
$var reg 1 ) clk $end
$var reg 3 * count_reset [2:0] $end
$var reg 3 + count_test [2:0] $end
$scope module uut $end
$var wire 1 # btn_diversion $end
$var wire 1 $ btn_energia $end
$var wire 1 % btn_hambre $end
$var wire 1 & btn_reset $end
$var wire 1 ' btn_salud $end
$var wire 1 ( btn_test $end
$var wire 1 ) clk $end
$var wire 3 , count_reset [2:0] $end
$var wire 3 - count_test [2:0] $end
$var reg 2 . btn_press_count [1:0] $end
$var reg 3 / display_out [2:0] $end
$var reg 4 0 nivel_diversion [3:0] $end
$var reg 4 1 nivel_energia [3:0] $end
$var reg 4 2 nivel_hambre [3:0] $end
$var reg 4 3 nivel_salud [3:0] $end
$var reg 7 4 seg_display [6:0] $end
$var reg 1 5 test_mode $end
$var reg 8 6 timer_diversion [7:0] $end
$var reg 8 7 timer_energia [7:0] $end
$var reg 8 8 timer_hambre [7:0] $end
$var reg 8 9 timer_salud [7:0] $end
$scope function get_seg_display $end
$var reg 4 : level [3:0] $end
$upscope $end
$upscope $end
$upscope $end
$enddefinitions $end
$comment Show the parameter values. $end
$dumpall
$end
#0
$dumpvars
bx :
b0 9
b0 8
b0 7
b0 6
05
b0 4
b1000 3
b1000 2
b1000 1
b1000 0
b0 /
b0 .
b0 -
b0 ,
b0 +
b0 *
0)
0(
0'
0&
0%
0$
0#
b0 "
b0 !
$end
#5000
b1 6
b1 8
b1 7
b1 9
b100 "
b100 /
b1111111 !
b1111111 4
b1000 :
1)
#10000
0)
#15000
b10 6
b10 8
b10 7
b10 9
1)
#20000
0)
1(
#25000
15
b11 6
b11 8
b11 7
b11 9
1)
#30000
0)
0(
#35000
1)
#40000
0)
#45000
1)
#50000
0)
1'
#55000
1)
#60000
0)
0'
#65000
1)
#70000
0)
#75000
1)
#80000
0)
1'
#85000
1)
#90000
0)
0'
#95000
1)
#100000
0)
#105000
1)
#110000
0)
1'
#115000
1)
#120000
0)
0'
#125000
1)
#130000
0)
#135000
1)
#140000
0)
1'
#145000
1)
#150000
0)
0'
#155000
1)
#160000
0)
#165000
1)
#170000
0)
1'
#175000
1)
#180000
0)
0'
#185000
1)
#190000
0)
#195000
1)
#200000
0)
1'
#205000
1)
#210000
0)
0'
#215000
1)
#220000
0)
#225000
1)
#230000
0)
1#
#235000
b1 .
b111 "
b111 /
1)
#240000
0)
0#
#245000
1)
#250000
0)
#255000
1)
#260000
0)
1#
#265000
b10 .
b1 0
1)
#270000
0)
0#
#275000
b110 !
b110 4
b11 "
b11 /
b1 :
1)
#280000
0)
#285000
1)
#290000
0)
1$
#295000
b11 .
b1 "
b1 /
1)
#300000
0)
0$
#305000
b101 "
b101 /
b1111111 !
b1111111 4
b1000 :
1)
#310000
0)
#315000
1)
#320000
0)
1$
#325000
b0 .
1)
#330000
0)
0$
#335000
1)
#340000
0)
#345000
1)
#350000
0)
1&
#355000
05
b1000 0
1)
#360000
0)
0&
#365000
b100 6
b100 8
b100 7
b100 9
1)
#370000
0)
#375000
b101 6
b101 8
b101 7
b101 9
1)
