mpu6050/compare.v
module COMPARE (
    input wire MCLK,
    input wire nRST,
    input wire TIC,
    input wire COMPLETED,
    output reg RESCAN,
    input wire [7:0] XREG,
    input wire [7:0] YREG,
    input wire [7:0] ZREG,
    output reg LEDX,
    output reg LEDY,
    output reg LEDZ,
    output reg SIGN
);

    function [7:0] magnitude;
        input [7:0] a;
        reg [7:0] ret;
        begin
            if (a[7] == 1'b1) begin
                ret = ~a + 1'b1;
            end else begin
                ret = a;
            end
            magnitude = ret;
        end
    endfunction

    wire [7:0] x2c = magnitude(XREG);
    wire [7:0] y2c = magnitude(YREG);
    wire [7:0] z2c = magnitude(ZREG);

    wire xy = (x2c > y2c) ? 1'b1 : 1'b0;
    wire xz = (x2c > z2c) ? 1'b1 : 1'b0;
    wire yz = (y2c > z2c) ? 1'b1 : 1'b0;

    wire ledx_a = xy & xz;
    wire ledy_a = ~xy & yz;
    wire ledz_a = ~xz & ~yz;

    always @(posedge MCLK or negedge nRST) begin
        if (!nRST) begin
            LEDX <= 1'b1;
            LEDY <= 1'b1;
            LEDZ <= 1'b1;
            SIGN <= 1'b1;
            RESCAN <= 1'b0;
        end else begin
            if (TIC) begin
                if (COMPLETED) begin
                    LEDX <= ~ledx_a;
                    LEDY <= ~ledy_a;
                    LEDZ <= ~ledz_a;
                    if (ledx_a) begin
                        SIGN <= ~XREG[7];
                    end else if (ledy_a) begin
                        SIGN <= ~YREG[7];
                    end else if (ledz_a) begin
                        SIGN <= ~ZREG[7];
                    end
                    RESCAN <= 1'b1;
                end else begin
                    RESCAN <= 1'b0;
                end
            end
        end
    end

endmodule

mpu6050/i2cmaster.v
module I2CMASTER (
    input wire MCLK,
    input wire nRST,
    input wire SRST,                        // synchronous reset
    input wire TIC,                         // i2c rate (bit rate x3)
    input wire [7:0] DIN,                   // data to send
    output reg [7:0] DOUT,                  // received data
    input wire RD,                          // read command
    input wire WE,                          // write command
    output reg NACK,                        // nack from slave
    output reg QUEUED,                      // operation (write or read cycle) is queued
    output reg DATA_VALID,                  // new data available on DOUT
    output reg STOP,
    output reg [2:0] STATUS,                // state machine state
    input wire SCL_IN,                      // i2c signals
    output reg SCL_OUT,
    input wire SDA_IN,
    output reg SDA_OUT
);

    parameter DEVICE = 8'h68; //8´h38

    // Definición de los estados
    parameter S_IDLE = 5'b00000,
              S_START = 5'b00001,
              S_SENDBIT = 5'b00010,
              S_WESCLUP = 5'b00011,
              S_WESCLDOWN = 5'b00100,
              S_CHECKACK = 5'b00101,
              S_CHECKACKUP = 5'b00110,
              S_CHECKACKDOWN = 5'b00111,
              S_WRITE = 5'b01000,
              S_PRESTOP = 5'b01001,
              S_STOP = 5'b01010,
              S_READ = 5'b01011,
              S_RECVBIT = 5'b01100,
              S_RDSCLUP = 5'b01101,
              S_RDSCLDOWN = 5'b01110,
              S_SENDACK = 5'b01111,
              S_SENDACKUP = 5'b10000,
              S_SENDACKDOWN = 5'b10001,
              S_RESTART = 5'b10010;

    // Variables de estado
    reg [4:0] state, next_state;
    reg [3:0] counter, next_counter;
    reg [7:0] shift;
    reg nackdet;
    reg sda_in_q, sda_in_qq;

    always @(*) begin
        next_counter = counter + 1;
    end

    always @(posedge MCLK or negedge nRST) begin
        if (!nRST) begin
            sda_in_q <= 1'b1;
            sda_in_qq <= 1'b1;
        end else if (MCLK) begin
            sda_in_q <= SDA_IN;
            sda_in_qq <= sda_in_q;
        end
    end

    always @(posedge MCLK or negedge nRST) begin
        if (!nRST) begin
            STATUS <= 3'b000;
            state <= S_IDLE;
            SCL_OUT <= 1'b1;
            SDA_OUT <= 1'b1;
            NACK <= 1'b0;
            QUEUED <= 1'b0;
            DATA_VALID <= 1'b0;
            DOUT <= 8'b0;
            counter <= 4'b0;
            nackdet <= 1'b0;
            shift <= 8'b0;
            STOP <= 1'b0;
        end else if (MCLK) begin
            if (SRST) begin
                state <= S_IDLE;
            end else begin
                case (state)
                    S_IDLE: begin
                        STATUS <= 3'b000;
                        SCL_OUT <= 1'b1;
                        SDA_OUT <= 1'b1;
                        NACK <= 1'b0;
                        QUEUED <= 1'b0;
                        DATA_VALID <= 1'b0;
                        DOUT <= 8'h01;
                        counter <= 4'b0;
                        STOP <= 1'b0;
                        if (TIC) begin
                            if (WE || RD) begin
                                state <= S_START;
                            end
                        end
                    end
                    S_START: begin
                        STATUS <= 3'b001;
                        SCL_OUT <= 1'b1;
                        SDA_OUT <= 1'b0; // start bit
                        NACK <= 1'b0;
                        QUEUED <= 1'b0;
                        STOP <= 1'b0;
                        DATA_VALID <= 1'b0;
                        if (TIC) begin
                            SCL_OUT <= 1'b0;
                            counter <= 4'b0000;
                            shift[7:1] <= DEVICE[6:0];
                            if (WE) begin
                                shift[0] <= 1'b0;
                                next_state <= S_WRITE;
                            end else begin
                                shift[0] <= 1'b1; // RD='1'
                                next_state <= S_READ;
                            end
                            state <= S_SENDBIT;
                        end
                    end
                    S_SENDBIT: begin
                        if (TIC) begin
                            STATUS <= 3'b010;
                            SCL_OUT <= 1'b0;
                            SDA_OUT <= shift[7];
                            shift[7:1] <= shift[6:0];
                            counter <= next_counter; 
                            NACK <= 1'b0;
                            QUEUED <= 1'b0;
                            STOP <= 1'b0;
                            DATA_VALID <= 1'b0;
                            state <= S_WESCLUP;
                        end
                    end
                    S_WESCLUP: begin
                        if (TIC) begin
                            NACK <= 1'b0;
                            QUEUED <= 1'b0;
                            DATA_VALID <= 1'b0;
                            SCL_OUT <= 1'b1;
                            state <= S_WESCLDOWN;
                        end
                    end
                    S_WESCLDOWN: begin
                        if (TIC) begin
                            NACK <= 1'b0;
                            QUEUED <= 1'b0;
                            STOP <= 1'b0;
                            DATA_VALID <= 1'b0;
                            SCL_OUT <= 1'b0;
                            if (counter[3]) begin
                                state <= S_CHECKACK;
                            end else begin
                                state <= S_SENDBIT;
                            end
                        end
                    end
                    S_CHECKACK: begin
                        if (TIC) begin
                            STATUS <= 3'b011;
                            SDA_OUT <= 1'b1;
                            NACK <= 1'b0;
                            QUEUED <= 1'b0;
                            STOP <= 1'b0;
                            DATA_VALID <= 1'b0;
                            SCL_OUT <= 1'b0;
                            state <= S_CHECKACKUP;    
                        end
                    end
                    S_CHECKACKUP: begin
                        if (TIC) begin
                            NACK <= 1'b0;
                            QUEUED <= 1'b0;
                            STOP <= 1'b0;
                            SCL_OUT <= 1'b1;
                            nackdet <= (sda_in_qq == 1'b1) ? 1'b1 : 1'b0;
                            state <= S_CHECKACKDOWN;    
                        end
                    end
                    S_CHECKACKDOWN: begin
                        if (TIC) begin
                            NACK <= 1'b0;
                            QUEUED <= 1'b0;
                            STOP <= 1'b0;
                            DATA_VALID <= 1'b0;
                            SCL_OUT <= 1'b0;
                            state <= next_state;    // S_WRITE or S_READ
                        end
                    end
                    S_WRITE: begin
                        if (nackdet) begin
                            NACK <= 1'b1;
                            SCL_OUT <= 1'b0;
                            if (TIC) begin
                                nackdet <= 1'b0;
                                SDA_OUT <= 1'b0;
                                state <= S_PRESTOP;
                            end
                        end else begin
                            if (WE) begin
                                shift <= DIN;
                                counter <= 4'b0000;
                                QUEUED <= 1'b1;
                                DATA_VALID <= 1'b0;
                                state <= S_SENDBIT;
                            end else if (RD) begin    
                                SCL_OUT <= 1'b0;
                                SDA_OUT <= 1'b1;
                                if (TIC) begin
                                    state <= S_RESTART; // for restart
                                end
                            end else begin
                                SCL_OUT <= 1'b0;
                                if (TIC) begin
                                    SDA_OUT <= 1'b0;
                                    state <= S_PRESTOP;
                                end
                            end
                        end
                    end
                    S_RESTART: begin
                        if (TIC) begin
                            state <= S_IDLE;
                        end
                    end
                    S_READ: begin
                        if (nackdet) begin
                            NACK <= 1'b1;
                            SCL_OUT <= 1'b0;
                            if (TIC) begin
                                nackdet <= 1'b0;
                                SDA_OUT <= 1'b0;
                                state <= S_PRESTOP;
                            end
                        end else begin
                            if (RD) begin
                                shift <= 8'b0;
                                counter <= 4'b0000;
                                QUEUED <= 1'b1;
                                state <= S_RECVBIT;
                            end else if (WE) begin    
                                SCL_OUT <= 1'b0;
                                SDA_OUT <= 1'b1;
                                if (TIC) begin
                                    state <= S_IDLE; // for restart
                                end
                            end else begin
                                SCL_OUT <= 1'b0;
                                if (TIC) begin
                                    SDA_OUT <= 1'b0;
                                    state <= S_PRESTOP;
                                end
                            end
                        end
                    end
                    S_RECVBIT: begin
                        if (TIC) begin
                            STATUS <= 3'b101;
                            SDA_OUT <= 1'b1;
                            SCL_OUT <= 1'b0;
                            counter <= next_counter; 
                            NACK <= 1'b0;
                            QUEUED <= 1'b0;
                            STOP <= 1'b0;
                            DATA_VALID <= 1'b0;
                            state <= S_RDSCLUP;
                        end
                    end
                    S_RDSCLUP: begin
                        if (TIC) begin
                            NACK <= 1'b0;
                            QUEUED <= 1'b0;
                            STOP <= 1'b0;
                            DATA_VALID <= 1'b0;
                            SCL_OUT <= 1'b1;
                            shift[7:1] <= shift[6:0];
                            shift[0] <= sda_in_qq;
                            state <= S_RDSCLDOWN;
                        end
                    end
                    S_RDSCLDOWN: begin
                        if (TIC) begin
                            NACK <= 1'b0;
                            QUEUED <= 1'b0;
                            STOP <= 1'b0;
                            DATA_VALID <= 1'b0;
                            SCL_OUT <= 1'b0;
                            if (counter[3]) begin
                                state <= S_SENDACK;
                            end else begin
                                state <= S_RECVBIT;
                            end
                        end
                    end
                    S_SENDACK: begin
                        if (TIC) begin
                            STATUS <= 3'b110;
                            SDA_OUT <= (RD) ? 1'b0 : 1'b1;  // last read 
                            DOUT <= shift;
                            NACK <= 1'b0;
                            QUEUED <= 1'b0;
                            STOP <= 1'b0;
                            DATA_VALID <= 1'b1;
                            SCL_OUT <= 1'b0;
                            state <= S_SENDACKUP;
                        end
                    end
                    S_SENDACKUP: begin
                        if (TIC) begin
                            NACK <= 1'b0;
                            QUEUED <= 1'b0;
                            STOP <= 1'b0;
                            DATA_VALID <= 1'b0;
                            SCL_OUT <= 1'b1;
                            state <= S_SENDACKDOWN;
                        end
                    end
                    S_SENDACKDOWN: begin
                        if (TIC) begin
                            NACK <= 1'b0;
                            QUEUED <= 1'b0;
                            STOP <= 1'b0;
                            DATA_VALID <= 1'b0;
                            SCL_OUT <= 1'b0;
                            state <= S_READ;
                        end
                    end
                    S_PRESTOP: begin
                        if (TIC) begin
                            STATUS <= 3'b111;
                            STOP <= 1'b1;
                            SCL_OUT <= 1'b1;
                            SDA_OUT <= 1'b0;
                            NACK <= 1'b0;
                            state <= S_STOP;
                        end
                    end
                    S_STOP: begin
                        if (TIC) begin
                            SCL_OUT <= 1'b1;
                            SDA_OUT <= 1'b1;
                            state <= S_IDLE;
                        end
                    end
                    default: state <= S_IDLE;
                endcase
            end
        end
    end

endmodule

mpu6050/mpu6050.v
module MPU6050 (
    input wire MCLK,
    input wire nRST,
    input wire TIC,
    output reg SRST,
    output reg [7:0] DOUT,
    output reg RD,
    output reg WE,
    input wire QUEUED,
    input wire NACK,
    input wire STOP,
    input wire DATA_VALID,
    input wire [7:0] DIN,
    output reg [3:0] ADR,
    output reg [7:0] DATA,
    output reg LOAD,
    output reg COMPLETED,
    input wire RESCAN
);

    // Definición de los estados
    parameter S_IDLE = 3'b000,
              S_PWRMGT0 = 3'b001,
              S_PWRMGT1 = 3'b010,
              S_READ0 = 3'b011,
              S_READ1 = 3'b100,
              S_STABLE = 3'b101;

    // Variable de estado
    reg [2:0] state;
    reg [3:0] adr_i;

    // Máquina de estados
    always @(posedge MCLK or negedge nRST) begin
        if (!nRST) begin
            SRST <= 1'b0;
            DOUT <= 8'b0;
            RD <= 1'b0;
            WE <= 1'b0;
            adr_i <= 4'b0;
            LOAD <= 1'b0;
            DATA <= 8'b11111111;
            COMPLETED <= 1'b0;
            state <= S_IDLE;
        end else begin
            case (state)
                S_IDLE: begin
                    if (TIC) begin
                        SRST <= 1'b0;
                        DOUT <= 8'b0;
                        RD <= 1'b0;
                        WE <= 1'b0;
                        adr_i <= 4'b0;
                        LOAD <= 1'b0;
                        DATA <= 8'b11111111;
                        COMPLETED <= 1'b0;
                        state <= S_PWRMGT0;
                    end
                end
                S_PWRMGT0: begin
                    if (TIC) begin
                        DOUT <= 8'h6B;
                        WE <= 1'b1;
                        RD <= 1'b0;
                        if (QUEUED) begin
                            DOUT <= 8'h00;
                            WE <= 1'b1;
                            RD <= 1'b0;
                            state <= S_PWRMGT1;
                        end else if (NACK) begin
                            state <= S_IDLE;
                        end
                    end
                end
                S_PWRMGT1: begin
                    if (TIC) begin
                        if (QUEUED) begin
                            DOUT <= 8'h00;
                            WE <= 1'b0;
                            RD <= 1'b0;
                            state <= S_READ0;
                        end else if (NACK) begin
                            state <= S_IDLE;
                        end
                    end
                end
                S_READ0: begin    
                    if (TIC) begin
                        if (STOP) begin
                            DOUT <= 8'h3B; // read 14 registers
                            WE <= 1'b1;
                            RD <= 1'b0;
                        end else if (QUEUED) begin
                            WE <= 1'b0;
                            RD <= 1'b1;
                            adr_i <= 4'b0;
                        end else if (DATA_VALID) begin
                            LOAD <= 1'b1;
                            DATA <= DIN;
                            state <= S_READ1;    
                        end else if (NACK) begin
                            state <= S_IDLE;
                        end    
                    end
                end
                S_READ1: begin
                    if (TIC) begin
                        if (DATA_VALID) begin
                            LOAD <= 1'b1;
                            DATA <= DIN;
                        end else if (QUEUED) begin
                            adr_i <= adr_i + 1;
                            if (adr_i == 4'b1100) begin // last one
                                WE <= 1'b0;
                                RD <= 1'b0;
                            end else begin
                                WE <= 1'b0;
                                RD <= 1'b1;
                            end
                        end else if (STOP) begin
                            state <= S_STABLE;
                        end else begin
                            LOAD <= 1'b0;
                        end
                    end
                end
                S_STABLE: begin
                    COMPLETED <= 1'b1;
                    if (TIC) begin
                        if (RESCAN) begin
                            state <= S_IDLE;
                        end
                    end
                end
            endcase
        end
    end

    always @* begin
        ADR = adr_i;
    end

endmodule

mpu6050/demo_mpu6050.v
module DEMO_MPU6050 (
    input wire MCLK,
    input wire RESET,
    inout wire SDA,
    inout wire SCL,
    output wire LEDX,
    output wire LEDY,
    output wire LEDZ,
    output wire LEDSIGN,
);

    // Internal signals
    wire TIC;
    wire SRST;
    wire [7:0] DOUT;
    wire RD;
    wire WE;
    wire QUEUED;
    wire NACK;
    wire STOP;
    wire DATA_VALID;
    wire [7:0] DIN;
    wire [3:0] ADR;
    wire [7:0] DATA;
    wire LOAD;
    wire COMPLETED;
    wire RESCAN;
    wire [2:0] STATUS;
    wire SCL_IN;
    wire SCL_OUT;
    wire SDA_IN;
    wire SDA_OUT;
    reg [7:0] counter = 0;
    wire nRST;

    // Output registers
    reg [7:0] XREG;
    reg [7:0] YREG;
    reg [7:0] ZREG;

    assign nRST = RESET;

    // Instantiate MPU6050 component
    MPU6050 I_MPU6050_0 (
        .MCLK(MCLK),
        .nRST(nRST),
        .TIC(TIC),
        .SRST(SRST),
        .DOUT(DIN),
        .RD(RD),
        .WE(WE),
        .QUEUED(QUEUED),
        .NACK(NACK),
        .STOP(STOP),
        .DATA_VALID(DATA_VALID),
        .DIN(DOUT),
        .ADR(ADR),
        .DATA(DATA),
        .LOAD(LOAD),
        .COMPLETED(COMPLETED),
        .RESCAN(RESCAN)
    );

    // Instantiate I2CMASTER component
    I2CMASTER #(.DEVICE(8'h68)) I_I2CMASTER_0 (
        .MCLK(MCLK),
        .nRST(nRST),
        .SRST(SRST),
        .TIC(TIC),
        .DIN(DIN),
        .DOUT(DOUT),
        .RD(RD),
        .WE(WE),
        .NACK(NACK),
        .QUEUED(QUEUED),
        .DATA_VALID(DATA_VALID),
        .STOP(STOP),
        .STATUS(STATUS),
        .SCL_IN(SCL_IN),
        .SCL_OUT(SCL_OUT),
        .SDA_IN(SDA_IN),
        .SDA_OUT(SDA_OUT)
    );

    // Instantiate COMPARE component
    COMPARE I_COMPARE_0 (
        .MCLK(MCLK),
        .nRST(nRST),
        .TIC(TIC),
        .COMPLETED(COMPLETED),
        .RESCAN(RESCAN),
        .XREG(XREG),
        .YREG(YREG),
        .ZREG(ZREG),
        .LEDX(LEDX),
        .LEDY(LEDY),
        .LEDZ(LEDZ),
        .SIGN(LEDSIGN)
    );

    // Generate TIC signal
    assign TIC = counter[7] & counter[5];

    // Counter process
    always @(posedge MCLK or negedge nRST) begin
        if (!nRST) begin
            counter <= 8'b0;
        end else if (TIC) begin
            counter <= 8'b0;
        end else begin
            counter <= counter + 1;
        end
    end

    // Registers process
    always @(posedge MCLK or negedge nRST) begin
        if (!nRST) begin
            XREG <= 8'b0;
            YREG <= 8'b0;
            ZREG <= 8'b0;
        end else if (TIC && LOAD) begin
            case (ADR)
                4'h0: XREG <= DATA; // Revisar para el acelerómetro
                4'h2: YREG <= DATA;
                4'h4: ZREG <= DATA;
            endcase
        end
    end

    // Open-drain configuration
    assign SCL = (SCL_OUT) ? 1'bz : 1'b0;
    assign SCL_IN = SCL;
    assign SDA = (SDA_OUT) ? 1'bz : 1'b0;
    assign SDA_IN = SDA;

endmodule

mpu6050/demo_mpu6050_tb.v
`include "mpu6050/mpu6050.v"
`include "mpu6050/i2cmaster.v"
`include "mpu6050/demo_mpu6050.v"
`include "mpu6050/compare.v"
`timescale 1ns / 1ps

module demo_mpu6050_tb;

    //Inputs son reg / Outputs son wire / Bidireccionales son wire
    reg MCLK;
    reg RESET;
    wire SDA;
    wire SCL;
    wire LEDX;
    wire LEDSIGN;

    DEMO_MPU6050 UUT (
        .MCLK(MCLK),
        .RESET(RESET),
        .SDA(SDA),
        .SCL(SCLA),
        .LEDX(LEDX),
        .LEDSIGN(LEDSIGN)
    );


    initial begin //Simula reloj
        MCLK = 0;
        forever begin
            MCLK = #10 ~MCLK;
        end
    end

    initial begin

        $dumpfile("demo_mpu6050_tb.vcd");
        $dumpvars(-1, UUT);

        //Inicializar variables
        MCLK = 0;
        RESET = 1;
        #1000000
        $finish;
    end

endmodule

build/demo_mpu6050_tb.vcd
$date
	Thu Aug 29 12:11:27 2024
$end
$version
	Icarus Verilog
$end
$timescale
	1ps
$end
$scope module demo_mpu6050_tb $end
$scope module UUT $end
$var wire 1 ! MCLK $end
$var wire 1 " RESET $end
$var wire 1 # SCL_IN $end
$var wire 1 $ SDA_IN $end
$var wire 1 % TIC $end
$var wire 1 & nRST $end
$var wire 1 ' WE $end
$var wire 1 ( STOP $end
$var wire 3 ) STATUS [2:0] $end
$var wire 1 * SRST $end
$var wire 1 + SDA_OUT $end
$var wire 1 , SDA $end
$var wire 1 - SCL_OUT $end
$var wire 1 . SCL $end
$var wire 1 / RESCAN $end
$var wire 1 0 RD $end
$var wire 1 1 QUEUED $end
$var wire 1 2 NACK $end
$var wire 1 3 LOAD $end
$var wire 1 4 LEDZ $end
$var wire 1 5 LEDY $end
$var wire 1 6 LEDX $end
$var wire 1 7 LEDSIGN $end
$var wire 8 8 DOUT [7:0] $end
$var wire 8 9 DIN [7:0] $end
$var wire 1 : DATA_VALID $end
$var wire 8 ; DATA [7:0] $end
$var wire 1 < COMPLETED $end
$var wire 4 = ADR [3:0] $end
$var reg 8 > XREG [7:0] $end
$var reg 8 ? YREG [7:0] $end
$var reg 8 @ ZREG [7:0] $end
$var reg 8 A counter [7:0] $end
$scope module I_COMPARE_0 $end
$var wire 1 ! MCLK $end
$var wire 1 % TIC $end
$var wire 8 B XREG [7:0] $end
$var wire 8 C YREG [7:0] $end
$var wire 8 D ZREG [7:0] $end
$var wire 1 E ledx_a $end
$var wire 1 F ledy_a $end
$var wire 1 G ledz_a $end
$var wire 1 & nRST $end
$var wire 8 H z2c [7:0] $end
$var wire 1 I yz $end
$var wire 8 J y2c [7:0] $end
$var wire 1 K xz $end
$var wire 1 L xy $end
$var wire 8 M x2c [7:0] $end
$var wire 1 < COMPLETED $end
$var reg 1 6 LEDX $end
$var reg 1 5 LEDY $end
$var reg 1 4 LEDZ $end
$var reg 1 / RESCAN $end
$var reg 1 7 SIGN $end
$scope function magnitude $end
$var reg 8 N a [7:0] $end
$var reg 8 O ret [7:0] $end
$upscope $end
$upscope $end
$scope module I_I2CMASTER_0 $end
$var wire 1 ! MCLK $end
$var wire 1 # SCL_IN $end
$var wire 1 $ SDA_IN $end
$var wire 1 % TIC $end
$var wire 1 & nRST $end
$var wire 1 ' WE $end
$var wire 1 * SRST $end
$var wire 1 0 RD $end
$var wire 8 P DIN [7:0] $end
$var parameter 8 Q DEVICE $end
$var parameter 5 R S_CHECKACK $end
$var parameter 5 S S_CHECKACKDOWN $end
$var parameter 5 T S_CHECKACKUP $end
$var parameter 5 U S_IDLE $end
$var parameter 5 V S_PRESTOP $end
$var parameter 5 W S_RDSCLDOWN $end
$var parameter 5 X S_RDSCLUP $end
$var parameter 5 Y S_READ $end
$var parameter 5 Z S_RECVBIT $end
$var parameter 5 [ S_RESTART $end
$var parameter 5 \ S_SENDACK $end
$var parameter 5 ] S_SENDACKDOWN $end
$var parameter 5 ^ S_SENDACKUP $end
$var parameter 5 _ S_SENDBIT $end
$var parameter 5 ` S_START $end
$var parameter 5 a S_STOP $end
$var parameter 5 b S_WESCLDOWN $end
$var parameter 5 c S_WESCLUP $end
$var parameter 5 d S_WRITE $end
$var reg 1 : DATA_VALID $end
$var reg 8 e DOUT [7:0] $end
$var reg 1 2 NACK $end
$var reg 1 1 QUEUED $end
$var reg 1 - SCL_OUT $end
$var reg 1 + SDA_OUT $end
$var reg 3 f STATUS [2:0] $end
$var reg 1 ( STOP $end
$var reg 4 g counter [3:0] $end
$var reg 1 h nackdet $end
$var reg 4 i next_counter [3:0] $end
$var reg 5 j next_state [4:0] $end
$var reg 1 k sda_in_q $end
$var reg 1 l sda_in_qq $end
$var reg 8 m shift [7:0] $end
$var reg 5 n state [4:0] $end
$upscope $end
$scope module I_MPU6050_0 $end
$var wire 1 : DATA_VALID $end
$var wire 8 o DIN [7:0] $end
$var wire 1 ! MCLK $end
$var wire 1 2 NACK $end
$var wire 1 1 QUEUED $end
$var wire 1 / RESCAN $end
$var wire 1 ( STOP $end
$var wire 1 % TIC $end
$var wire 1 & nRST $end
$var parameter 3 p S_IDLE $end
$var parameter 3 q S_PWRMGT0 $end
$var parameter 3 r S_PWRMGT1 $end
$var parameter 3 s S_READ0 $end
$var parameter 3 t S_READ1 $end
$var parameter 3 u S_STABLE $end
$var reg 4 v ADR [3:0] $end
$var reg 1 < COMPLETED $end
$var reg 8 w DATA [7:0] $end
$var reg 8 x DOUT [7:0] $end
$var reg 1 3 LOAD $end
$var reg 1 0 RD $end
$var reg 1 * SRST $end
$var reg 1 ' WE $end
$var reg 4 y adr_i [3:0] $end
$var reg 3 z state [2:0] $end
$upscope $end
$upscope $end
$upscope $end
$enddefinitions $end
$comment Show the parameter values. $end
$dumpall
b101 u
b100 t
b11 s
b10 r
b1 q
b0 p
b1000 d
b11 c
b100 b
b1010 a
b1 `
b10 _
b10000 ^
b10001 ]
b1111 \
b10010 [
b1100 Z
b1011 Y
b1101 X
b1110 W
b1001 V
b0 U
b110 T
b111 S
b101 R
b1101000 Q
$end
#0
$dumpvars
b0 z
bx y
bx x
bx w
bx v
bx o
bx n
bx m
xl
xk
bx j
bx i
xh
bx g
bx f
bx e
bx P
b1 O
b1 N
b1 M
0L
0K
b1 J
0I
b1 H
1G
0F
0E
b1 D
b1 C
b1 B
b0 A
b1 @
b1 ?
b1 >
bx =
x<
bx ;
x:
bx 9
bx 8
x7
x6
x5
x4
x3
x2
x1
x0
x/
x.
x-
x,
x+
x*
bx )
x(
x'
1&
0%
x$
x#
1"
0!
$end
#10000
b0 n
b1 A
1!
#20000
0!
#30000
b1 i
z$
z,
z#
z.
b10 A
0(
b0 g
b1 8
b1 e
b1 o
0:
01
02
1+
1-
b0 )
b0 f
1!
#40000
0!
#50000
zk
b11 A
1!
#60000
0!
#70000
b100 A
zl
1!
#80000
0!
#90000
b101 A
1!
#100000
0!
#110000
b110 A
1!
#120000
0!
#130000
b111 A
1!
#140000
0!
#150000
b1000 A
1!
#160000
0!
#170000
b1001 A
1!
#180000
0!
#190000
b1010 A
1!
#200000
0!
#210000
b1011 A
1!
#220000
0!
#230000
b1100 A
1!
#240000
0!
#250000
b1101 A
1!
#260000
0!
#270000
b1110 A
1!
#280000
0!
#290000
b1111 A
1!
#300000
0!
#310000
b10000 A
1!
#320000
0!
#330000
b10001 A
1!
#340000
0!
#350000
b10010 A
1!
#360000
0!
#370000
b10011 A
1!
#380000
0!
#390000
b10100 A
1!
#400000
0!
#410000
b10101 A
1!
#420000
0!
#430000
b10110 A
1!
#440000
0!
#450000
b10111 A
1!
#460000
0!
#470000
b11000 A
1!
#480000
0!
#490000
b11001 A
1!
#500000
0!
#510000
b11010 A
1!
#520000
0!
#530000
b11011 A
1!
#540000
0!
#550000
b11100 A
1!
#560000
0!
#570000
b11101 A
1!
#580000
0!
#590000
b11110 A
1!
#600000
0!
#610000
b11111 A
1!
#620000
0!
#630000
b100000 A
1!
#640000
0!
#650000
b100001 A
1!
#660000
0!
#670000
b100010 A
1!
#680000
0!
#690000
b100011 A
1!
#700000
0!
#710000
b100100 A
1!
#720000
0!
#730000
b100101 A
1!
#740000
0!
#750000
b100110 A
1!
#760000
0!
#770000
b100111 A
1!
#780000
0!
#790000
b101000 A
1!
#800000
0!
#810000
b101001 A
1!
#820000
0!
#830000
b101010 A
1!
#840000
0!
#850000
b101011 A
1!
#860000
0!
#870000
b101100 A
1!
#880000
0!
#890000
b101101 A
1!
#900000
0!
#910000
b101110 A
1!
#920000
0!
#930000
b101111 A
1!
#940000
0!
#950000
b110000 A
1!
#960000
0!
#970000
b110001 A
1!
#980000
0!
#990000
b110010 A
1!
#1000000
0!
#1010000
b110011 A
1!
#1020000
0!
#1030000
b110100 A
1!
#1040000
0!
#1050000
b110101 A
1!
#1060000
0!
#1070000
b110110 A
1!
#1080000
0!
#1090000
b110111 A
1!
#1100000
0!
#1110000
b111000 A
1!
#1120000
0!
#1130000
b111001 A
1!
#1140000
0!
#1150000
b111010 A
1!
#1160000
0!
#1170000
b111011 A
1!
#1180000
0!
#1190000
b111100 A
1!
#1200000
0!
#1210000
b111101 A
1!
#1220000
0!
#1230000
b111110 A
1!
#1240000
0!
#1250000
b111111 A
1!
#1260000
0!
#1270000
b1000000 A
1!
#1280000
0!
#1290000
b1000001 A
1!
#1300000
0!
#1310000
b1000010 A
1!
#1320000
0!
#1330000
b1000011 A
1!
#1340000
0!
#1350000
b1000100 A
1!
#1360000
0!
#1370000
b1000101 A
1!
#1380000
0!
#1390000
b1000110 A
1!
#1400000
0!
#1410000
b1000111 A
1!
#1420000
0!
#1430000
b1001000 A
1!
#1440000
0!
#1450000
b1001001 A
1!
#1460000
0!
#1470000
b1001010 A
1!
#1480000
0!
#1490000
b1001011 A
1!
#1500000
0!
#1510000
b1001100 A
1!
#1520000
0!
#1530000
b1001101 A
1!
#1540000
0!
#1550000
b1001110 A
1!
#1560000
0!
#1570000
b1001111 A
1!
#1580000
0!
#1590000
b1010000 A
1!
#1600000
0!
#1610000
b1010001 A
1!
#1620000
0!
#1630000
b1010010 A
1!
#1640000
0!
#1650000
b1010011 A
1!
#1660000
0!
#1670000
b1010100 A
1!
#1680000
0!
#1690000
b1010101 A
1!
#1700000
0!
#1710000
b1010110 A
1!
#1720000
0!
#1730000
b1010111 A
1!
#1740000
0!
#1750000
b1011000 A
1!
#1760000
0!
#1770000
b1011001 A
1!
#1780000
0!
#1790000
b1011010 A
1!
#1800000
0!
#1810000
b1011011 A
1!
#1820000
0!
#1830000
b1011100 A
1!
#1840000
0!
#1850000
b1011101 A
1!
#1860000
0!
#1870000
b1011110 A
1!
#1880000
0!
#1890000
b1011111 A
1!
#1900000
0!
#1910000
b1100000 A
1!
#1920000
0!
#1930000
b1100001 A
1!
#1940000
0!
#1950000
b1100010 A
1!
#1960000
0!
#1970000
b1100011 A
1!
#1980000
0!
#1990000
b1100100 A
1!
#2000000
0!
#2010000
b1100101 A
1!
#2020000
0!
#2030000
b1100110 A
1!
#2040000
0!
#2050000
b1100111 A
1!
#2060000
0!
#2070000
b1101000 A
1!
#2080000
0!
#2090000
b1101001 A
1!
#2100000
0!
#2110000
b1101010 A
1!
#2120000
0!
#2130000
b1101011 A
1!
#2140000
0!
#2150000
b1101100 A
1!
#2160000
0!
#2170000
b1101101 A
1!
#2180000
0!
#2190000
b1101110 A
1!
#2200000
0!
#2210000
b1101111 A
1!
#2220000
0!
#2230000
b1110000 A
1!
#2240000
0!
#2250000
b1110001 A
1!
#2260000
0!
#2270000
b1110010 A
1!
#2280000
0!
#2290000
b1110011 A
1!
#2300000
0!
#2310000
b1110100 A
1!
#2320000
0!
#2330000
b1110101 A
1!
#2340000
0!
#2350000
b1110110 A
1!
#2360000
0!
#2370000
b1110111 A
1!
#2380000
0!
#2390000
b1111000 A
1!
#2400000
0!
#2410000
b1111001 A
1!
#2420000
0!
#2430000
b1111010 A
1!
#2440000
0!
#2450000
b1111011 A
1!
#2460000
0!
#2470000
b1111100 A
1!
#2480000
0!
#2490000
b1111101 A
1!
#2500000
0!
#2510000
b1111110 A
1!
#2520000
0!
#2530000
b1111111 A
1!
#2540000
0!
#2550000
b10000000 A
1!
#2560000
0!
#2570000
b10000001 A
1!
#2580000
0!
#2590000
b10000010 A
1!
#2600000
0!
#2610000
b10000011 A
1!
#2620000
0!
#2630000
b10000100 A
1!
#2640000
0!
#2650000
b10000101 A
1!
#2660000
0!
#2670000
b10000110 A
1!
#2680000
0!
#2690000
b10000111 A
1!
#2700000
0!
#2710000
b10001000 A
1!
#2720000
0!
#2730000
b10001001 A
1!
#2740000
0!
#2750000
b10001010 A
1!
#2760000
0!
#2770000
b10001011 A
1!
#2780000
0!
#2790000
b10001100 A
1!
#2800000
0!
#2810000
b10001101 A
1!
#2820000
0!
#2830000
b10001110 A
1!
#2840000
0!
